Workbook

Sheet 1. Dashboard & Jun-26
A1: SHEET 1 - FUND DASHBOARD & JUNE 2026 RESTATEMENT
A2: Konigstein Affordable Housing Fund (KAHF) — GIPF 99.01% / Konigstein Capital 0.99%. All amounts N$ (NAD). Blue = source figure typed from a named document. Black = formula. Green = link to another tab in this workbook.
A4: A. CAPITAL FROM GIPF — the input side
A5: Total capital allocation approved for investment (fund level) | B5: 446420000 | F5: Fund drawdown register (KAHF_Damask Performance (CHQ) > Drawdowns), row 23 column P.
A6: GIPF capital account at 31 July 2026 | B6: 188072936 | F6: KAHF trial balance as at 28-02-2026, account 5100/020.
A7: GIPF capital account at 28 Feb 2025 (comparative) | B7: 108341357 | F7: Same trial balance, prior-year column. NOTE: a second trial balance in the pack shows N$131,984,039 at the same date — unreconciled.
A8: Konigstein Capital capital account at 28 Feb 2026 | B8: 1518374 | F8: Account 5100/030. GIPF share of paid-in capital = 99.01%.
A9: Movement in GIPF capital, Feb-25 to Jul-26 | B9: =B6-B7 -> 79731579 | F9: Capital called from GIPF during the year.
A10: Capital still callable from GIPF (undrawn) | B10: 2.519026e+08 | F10: Fund drawdown register row 106. Fund total N$254,421,625.91 of which KC N$2,519,025.97.
A11: Management fees charged to the fund, inception to date | B11: 46051257 | F11: Fund drawdown register row 102.
A12: Trust expenses, inception to date | B12: 2748719.5 | F12: Fund drawdown register row 103.
A14: B. DISTRIBUTIONS TO GIPF — the output side
A15: Cash distributions paid out of KAHF to GIPF, inception to date | B15: 0 | F15: NO distribution to GIPF is recorded anywhere in the Fund Model folder. The GIPF capital account shows contributions only, with no drawings. Every "distribution" in this model is a repayment from a project INTO the fund, available for recycling.
A16: Project repayments received into the fund, inception to date | B16: ='2. Project Performance'!D19 -> 2.078e+08 | F16: Sheet 2 portfolio total — ties to the Ledger and to Sheet 4.
A17: of which recycled into new projects or held as fund liquidity | B17: =B16 -> 2.078e+08 | F17: All project repayments have been redeployed or are held in fund liquidity — none has left the fund.
A18: Fund liquidity — Capricorn High Yield Fund at 31 Jul 2026 | B18: 53519718 | F18: CAM investment statement, client 13853366, period 01-31 Jul 2026 (statement dated 11-08-2026).
A19: Fund liquidity — Bank Windhoek current account at 28 Feb 2026 | B19: 6109913.6 | F19: KAHF trial balance 28-02-2026, account 8400/000.
A20: Interest earned on fund liquidity, Jul 2026 | B20: 343457.63 | F20: CAM Interest July 2026 tab, KAHF - Interest Schedule July 2026.
A22: C. BASELINE PERFORMANCE AS AT 30 JUNE 2026
A23: Capital deployed into projects, inception to 30-Jun-26 | B23: =SUMIFS(Ledger!$D$5:$D$107,Ledger!$A$5:$A$107,"<="&DATE(2026,6,30)) -> -3.5238751e+08 | F23: SUMIFS over the Ledger tab, date on or before 30-06-2026.
A24: Distributions received from projects, inception to 30-Jun-26 | B24: =SUMIFS(Ledger!$E$5:$E$107,Ledger!$A$5:$A$107,"<="&DATE(2026,6,30)) -> 2.078e+08
A25: Net capital outstanding at 30-Jun-26 | B25: =B23+B24 -> -1.4458751e+08
A26: Portfolio carrying value / NAV at the June-26 baseline | B26: =SUMIF('2. Project Performance'!B5:B18,"Active*",'2. Project Performance'!I5:I18) -> 1.1769638e+08 | F26: Sum of the carrying values on Sheet 2 — see that tab for the valuation date behind each one.
A27: Cash Available | B27: =+Balance_Sheet_July_2026!C20 -> 67037159
A28: Total value to the fund (distributions + NAV + Cash) | B28: =B24+B26+B27 -> 3.9253354e+08
A29: TVPI on capital deployed at 30-Jun-26 | B29: =B28/-B23 -> 1.1139258
A30: Net gain / (deficit) over capital deployed | B30: =B28+B23 -> 40146028
A31: Interest earned across the loan book, Jan-Jul 2026 | B31: 14897942 | F31: KAHF - Interest Schedule July 2026, "Interest July 2026" tab, total column J.
A33: D. PORTFOLIO SHAPE AT THE REPORTING DATE
A34: Projects in the pack | B34: 14 | F34: Sheet 2 — 10 active, 4 completed.
A35: Completed / fully redeemed projects | B35: 4 | F35: Heavens Ark, NIC Otjomuise Ext 10, Duma Tau, LIH Nkurenkuru Ph 1.
A36: Total planned units across the portfolio | B36: ='3. Delivery Outputs'!B37 -> 6019 | F36: Sheet 3 portfolio total.
A37: Units delivered to date (where the pack records a count) | B37: ='3. Delivery Outputs'!D37 -> 200 | F37: Blanks on Sheet 3 are unrecorded, not zero.
A41: Reading this sheet: The whole of section D is one quarter — Jul to Sep 2026 — and it is dominated by two repayments.
A42: The single most important disclosure on this page is line B (row 16).
A143: D. RESTATEMENT — movements since the June 2026 baseline
A144: Capital deployed after 30-Jun-26 | B144: =SUMIFS(Ledger!$D$5:$D$107,Ledger!$A$5:$A$107,">"&DATE(2026,6,30)) -> -11616720 | F144: Tama Estates Phase 1 N$4,466,720 and PAM Tree notice 089 N$4,150,000, plus C-Breeze / Tama fee offsets.
A145: Distributions received after 30-Jun-26 | B145: =SUMIFS(Ledger!$E$5:$E$107,Ledger!$A$5:$A$107,">"&DATE(2026,6,30)) -> 0 | F145: PAM Tree N$28,390,200 and Turnstone Villas N$14,000,000 — the single largest repayment quarter in the fund's history.
A146: Net movement since the baseline | B146: =B144+B145 -> -11616720
A147: Restated capital deployed, inception to date | B147: ='2. Project Performance'!C19 -> -3.7100423e+08
A148: Restated distributions received, inception to date | B148: ='2. Project Performance'!D19 -> 2.078e+08
A149: Restated net capital outstanding | B149: =B147+B148 -> -1.6320423e+08
A150: Restated TVPI | B150: ='2. Project Performance'!K19 -> 0.93196526

Sheet 2. Project Performance
A1: SHEET 2 — PROJECT-BY-PROJECT PERFORMANCE
A2: Every project in the Fund Model folder. Capital deployed and distributed are SUMIFS over the Ledger tab.
A4: Project | B4: Status | C4: Capital deployed (N$) | D4: Capital distributed (N$) | E4: Net cash position (N$) | F4: Approved deal size / facility (N$) | G4: Total project cost (N$) | H4: Gross development value (N$) | I4: Carrying value / NAV (N$) | J4: Total value (dist. + NAV) | K4: MOIC / TVPI | L4: Updated IRR | M4: IRR basis and source
A5: Aromatic Fresh Notes Investments Pty Ltd - Erf 1470 Khomasdal | B5: Active | C5: =SUMIFS(Ledger!$D$5:$D$109,Ledger!$B$5:$B$109,$A5) -> -95611595 | D5: =SUMIFS(Ledger!$E$5:$E$109,Ledger!$B$5:$B$109,$A5) -> 37033391 | E5: =C5+D5 -> -58578204 | F5: 63500000 | I5: 40105521 | J5: =D5+I5 -> 77138912 | K5: =IFERROR(J5/-C5,"n/a") -> 0.80679453 | L5: 0.0541 | M5: Return Dashboard C8 — realised XIRR. Snapshot 'Expected IRR' on Contract Parameters K103 = 4.0%.
A6: Damask Dunescape Villas | B6: Completed | C6: =SUMIFS(Ledger!$D$5:$D$109,Ledger!$B$5:$B$109,$A6) -> -25551000 | D6: =SUMIFS(Ledger!$E$5:$E$109,Ledger!$B$5:$B$109,$A6) -> 24000000 | E6: =C6+D6 -> -1551000 | F6: 39000000 | I6: 12958884 | J6: =D6+I6 -> 36958884 | K6: =IFERROR(J6/-C6,"n/a") -> 1.446475 | L6: 0.3603 | M6: Historical Ledgers F30 — XIRR incl. NAV N$8,508,452 and PM fees N$7,177,927.
A7: PAM Tree Investment Pty Ltd - Kuisebmund Erf 5758 | B7: Active | C7: =SUMIFS(Ledger!$D$5:$D$109,Ledger!$B$5:$B$109,$A7) -> -45000000 | D7: =SUMIFS(Ledger!$E$5:$E$109,Ledger!$B$5:$B$109,$A7) -> 0 | E7: =C7+D7 -> -45000000 | F7: 45000000 | I7: 35672548 | J7: =D7+I7 -> 35672548 | K7: =IFERROR(J7/-C7,"n/a") -> 0.79272329 | L7: 0.24 | M7: Contract Parameters D31 — reported/projected. Workbook XIRR cell is broken (REF-error / mis-summed -33.5%).
A8: Mossy Wood Notes Investments- Turnstone Villas | B8: Completed | C8: =SUMIFS(Ledger!$D$5:$D$109,Ledger!$B$5:$B$109,$A8) -> -16300000 | D8: =SUMIFS(Ledger!$E$5:$E$109,Ledger!$B$5:$B$109,$A8) -> 0 | E8: =C8+D8 -> -16300000 | F8: 16300000 | I8: 4911828 | J8: =D8+I8 -> 4911828 | K8: =IFERROR(J8/-C8,"n/a") -> 0.30133914 | L8: -0.106 | M8: Return Dashboard D19 — realised XIRR, event-dated, unrealised NAV excluded.
A9: Lithon Developers - Nkurenkuru Ext 2 | B9: Active | C9: =SUMIFS(Ledger!$D$5:$D$109,Ledger!$B$5:$B$109,$A9) -> -5500000 | D9: =SUMIFS(Ledger!$E$5:$E$109,Ledger!$B$5:$B$109,$A9) -> 0 | E9: =C9+D9 -> -5500000 | F9: 5500000 | I9: 1037365.9 | J9: =D9+I9 -> 1037365.9 | K9: =IFERROR(J9/-C9,"n/a") -> 0.18861199 | L9: 0.3011 | M9: Historical Ledgers D111 — IRR incl. terminal NAV. Cash-only realised IRR = 15.76% (D110). The 16.08% on the Return Dashboard is the effective annual rate of the 15% NACM coupon, not an IRR.
A10: Damask- Mondesa Palms | B10: Active | C10: =SUMIFS(Ledger!$D$5:$D$109,Ledger!$B$5:$B$109,$A10) -> -15000000 | D10: =SUMIFS(Ledger!$E$5:$E$109,Ledger!$B$5:$B$109,$A10) -> 0 | E10: =C10+D10 -> -15000000 | F10: 28000000 | G10: 31277884 | H10: 42400000 | I10: 12958884 | J10: =D10+I10 -> 12958884 | K10: =IFERROR(J10/-C10,"n/a") -> 0.8639256 | L10: 0.1894 | M10: Dashboard E9 — realised IRR base case. PROVISIONAL: facility size, rate, first-draw date and unit price are all placeholders.
A11: Blue Mont Pty Ltd The Ridge | B11: Active | C11: =SUMIFS(Ledger!$D$5:$D$109,Ledger!$B$5:$B$109,$A11) -> -20000000 | D11: =SUMIFS(Ledger!$E$5:$E$109,Ledger!$B$5:$B$109,$A11) -> 0 | E11: =C11+D11 -> -20000000 | F11: 30000000 | G11: 27926209 | H11: 38000000 | I11: 13022186 | J11: =D11+I11 -> 13022186 | K11: =IFERROR(J11/-C11,"n/a") -> 0.65110928 | L11: 0.1853 | M11: Dashboard E9 — realised IRR base case.
A12: Mango Cove - Otjomuise Ext 10 | B12: Active | C12: =SUMIFS(Ledger!$D$5:$D$109,Ledger!$B$5:$B$109,$A12) -> -12000000 | D12: =SUMIFS(Ledger!$E$5:$E$109,Ledger!$B$5:$B$109,$A12) -> 0 | E12: =C12+D12 -> -12000000 | F12: 20000000 | I12: 4827160 | J12: =D12+I12 -> 4827160 | K12: =IFERROR(J12/-C12,"n/a") -> 0.40226333 | L12: n/a | M12: No IRR in the pack. Interest schedule prices the loan at 14.0% NACM.
A13: Block 9 - C-Breeze Heights | B13: Active | C13: =SUMIFS(Ledger!$D$5:$D$109,Ledger!$B$5:$B$109,$A13) -> -4389111.1 | D13: =SUMIFS(Ledger!$E$5:$E$109,Ledger!$B$5:$B$109,$A13) -> 0 | E13: =C13+D13 -> -4389111.1 | F13: 5000000 | G13: 26748597 | H13: 31785000 | I13: 4822787 | J13: =D13+I13 -> 4822787 | K13: =IFERROR(J13/-C13,"n/a") -> 1.0988072 | L13: 0.18 | M13: Vert Development Model — 'Equity - Mezzanine' levered IRR (per instruction). Interest schedule: 15.37% base, 18.0% after participation top-up.
A14: Block 9- Tama Estates | B14: Active | C14: =SUMIFS(Ledger!$D$5:$D$109,Ledger!$B$5:$B$109,$A14) -> -4466720.5 | D14: =SUMIFS(Ledger!$E$5:$E$109,Ledger!$B$5:$B$109,$A14) -> 0 | E14: =C14+D14 -> -4466720.5 | F14: 11000000 | G14: 113500309 | H14: 127130303 | I14: 5249926.2 | J14: =D14+I14 -> 5249926.2 | K14: =IFERROR(J14/-C14,"n/a") -> 1.1753425 | L14: 0.208 | M14: Vert Development Model — 'Equity - Investor' levered IRR (per instruction). Interest schedule XIRR on Phase-1 drawn capital = 18.35%.
A15: Duma Tau — Kronlein | B15: Completed | C15: =SUMIFS(Ledger!$D$5:$D$109,Ledger!$B$5:$B$109,$A15) -> -36109399 | D15: =SUMIFS(Ledger!$E$5:$E$109,Ledger!$B$5:$B$109,$A15) -> 42507268 | E15: =C15+D15 -> 6397868.7 | F15: 28000000 | I15: 1197995 | J15: =D15+I15 -> 43705263 | K15: =IFERROR(J15/-C15,"n/a") -> 1.210357 | L15: 0.1289 | M15: Return Dashboard D19 — event-dated XIRR. Supersedes 11.69% and 15.86% previously reported.
A16: LIH- Nkurenkuru Ph 1 | B16: Completed | C16: =SUMIFS(Ledger!$D$5:$D$109,Ledger!$B$5:$B$109,$A16) -> -19076405 | D16: =SUMIFS(Ledger!$E$5:$E$109,Ledger!$B$5:$B$109,$A16) -> 21306076 | E16: =C16+D16 -> 2229670.5 | F16: 18000000 | I16: 1197968.2 | J16: =D16+I16 -> 22504044 | K16: =IFERROR(J16/-C16,"n/a") -> 1.1796795 | L16: 0.1098 | M16: Return Dashboard D19 — XIRR off Net LP cash flow.
A17: NIC - Otjomuise Ext 10 | B17: Completed | C17: =SUMIFS(Ledger!$D$5:$D$109,Ledger!$B$5:$B$109,$A17) -> -7000000 | D17: =SUMIFS(Ledger!$E$5:$E$109,Ledger!$B$5:$B$109,$A17) -> 7353424.5 | E17: =C17+D17 -> 353424.49 | F17: 7000000 | I17: 0 | J17: =D17+I17 -> 7353424.5 | K17: =IFERROR(J17/-C17,"n/a") -> 1.0504892 | L17: 0.1791 | M17: Return Dashboard D19 — realised XIRR, facility fully redeemed 28-Apr-23.
A18: MPG _ Heaven's Ark — Otjomuise Lifestyle Estate | B18: Completed | C18: =SUMIFS(Ledger!$D$5:$D$109,Ledger!$B$5:$B$109,$A18) -> -65000000 | D18: =SUMIFS(Ledger!$E$5:$E$109,Ledger!$B$5:$B$109,$A18) -> 75599843 | E18: =C18+D18 -> 10599843 | F18: 65000000 | I18: 0 | J18: =D18+I18 -> 75599843 | K18: =IFERROR(J18/-C18,"n/a") -> 1.1630745 | L18: 0.1857 | M18: Return Dashboard D19 — XIRR off Net LP cash flow, fully redeemed.
A19: PORTFOLIO TOTAL | C19: =SUM(C5:C18) -> -3.7100423e+08 | D19: =SUM(D5:D18) -> 2.078e+08 | E19: =SUM(E5:E18) -> -1.6320423e+08 | F19: =SUM(F5:F18) -> 381300000 | G19: =SUM(G5:G18) -> 1.99453e+08 | H19: =SUM(H5:H18) -> 239315303 | I19: =SUM(I5:I18) -> 1.3796305e+08 | J19: =SUM(J5:J18) -> 3.4576306e+08 | K19: =IFERROR(J19/-C19,"n/a") -> 0.93196526 | L19: =(L5+L18+L17+L16+L15+L14+L13+L11+L10+L9-L8+L6+L7+L20)/13 -> 0.18674615

Sheet 3. Delivery Outputs
A1: SHEET 3 — DELIVERY OUTPUTS (units built vs planned)
A2: Planned units for the six named projects are hardcoded per instruction (blue). Every other figure is read from the project model named in the last column. Blank = the pack records no figure — do not read blank as zero.
A4: Project | B4: Total planned units | C4: Erven / scope | D4: Units built to date | E4: Units sold / transferred | F4: % complete | G4: Units outstanding | H4: Delivery status | I4: Source in the model pack
A5: A. ACTIVE PROJECTS — planned units hardcoded per instruction
A6: PAM Tree (Erf 5758) | B6: 189 | C6: Erf 5758 Kuisebmund, Walvis Bay — 219 plots on the General Plan | E6: 16 | G6: =IF(ISNUMBER(D6),B6-D6,"") | H6: Phase 1 of 3 under way | I6: Contract Parameters D26 (219 plots), D28 (16 units sold). No units-built count is recorded in the workbook.
A7: C-Breeze Heights | B7: 13 | C7: Erf 1329, CBD Swakopmund — single erf | D7: 0 | E7: 0 | G7: =IF(ISNUMBER(D7),B7-D7,"") -> 13 | H7: Vertical construction Feb-26 to Oct-26 | I7: Vert Development Model p.1 — 13 units, vertical end Oct-2026, transfers end Dec-2026. No completions recorded.
A8: Tama Estates | B8: 87 | C8: Erf 673 Tamariskia — 8 stages | D8: 0 | E8: 0 | G8: =IF(ISNUMBER(D8),B8-D8,"") -> 87 | H8: Horizontal from Apr-26; vertical from Jul-26 | I8: Vert Development Model p.1 — 87 units, vertical start Jul-2026, transfers start Nov-2026.
A9: Mondesa Palms | B9: 134 | C9: 134 units across 3 erven (4420 / 4421 / 4422) | D9: 0 | E9: 0 | F9: 0.15 | G9: =IF(ISNUMBER(D9),B9-D9,"") -> 134 | H9: Erf 4420 (40 units) in construction | I9: Programme F7 — 15% complete at 18-Jun-26; practical completion forecast 09-Feb-27. Model covers Erf 4420 only.
A10: The Ridge — Rocky Crest Ext 4 | B10: 38 | C10: Erf R/E 1502 & Erf 1757, Rocky Crest Ext 4 | D10: 0 | E10: 0 | G10: =IF(ISNUMBER(D10),B10-D10,"") -> 38 | H10: Foundations from Jun-26 | I10: BudgetActual D6 — construction actual N$0 against a N$20.0m budget; practical completion 01-Mar-27.
A11: Mango Cove (Otjomuise Ext 10) | B11: 109 | C11: 109 units across 6 erven | D11: 0 | G11: =IF(ISNUMBER(D11),B11-D11,"") -> 109 | H11: Early drawdown stage | I11: No delivery data in the pack. Unit count taken from the KAHF Projects schedule.
A12: Sub-total — hardcoded plan | B12: =SUM(B6:B11) -> 570 | D12: =SUM(D6:D11) -> 0 | E12: =SUM(E6:E11) -> 16 | G12: =B12-D12 -> 570
A14: B. OTHER PROJECTS IN THE PACK — planned units read from the models
A15: Erf 1470 Khomasdal | B15: 255 | C15: 6 erven; 135 units to be delivered via KAHF (N$27.13m) + FNB (N$20m) | D15: 93 | F15: 0.41 | G15: =IF(ISNUMBER(D15),B15-D15,"") -> 162 | H15: Phase 2 (Erf 7077, 24 units) under way | I15: Contract Parameters C29 (93 constructed), C30 (255 to be constructed), K96 (229 housing units), K102 (41% complete). The three unit counts in this workbook do not agree.
A16: Dunescape Villas (Erf 5159) | B16: 40 | C16: Erf R/E 5159 Ext 15, Swakopmund | D16: 40 | E16: 40 | F16: 1 | G16: =IF(ISNUMBER(D16),B16-D16,"") -> 0 | H16: Complete — all units sold and transferred | I16: Cashflow B48 — 100% complete, all 40 units sold and transferred at 30-Apr-26. Contract Parameters M91 flags only 13 units traceable to a transfer schedule.
A17: Turnstone Villas (Erf 8939) | B17: 17 | C17: Erf 8939 Ext 35, Swakopmund | D17: 17 | E17: 13 | F17: 1 | G17: =IF(ISNUMBER(D17),B17-D17,"") -> 0 | H17: Construction complete 09-Oct-25 | I17: Contract Parameters E97 — construction complete, 13 of 17 transferred, all 17 sold; B112 — 4 sold not yet transferred.
A18: Lithon Nkurenkuru Ext 2 | B18: 37 | C18: Erf 845, Nkurenkuru Ext 2 — Phase 2 | D18: 33 | F18: 0.89 | G18: =IF(ISNUMBER(D18),B18-D18,"") -> 4 | H18: 33 of 37 houses complete at 30-Sep-25 | I18: Cashflow C60/C61/C62 — 37 planned, 33 completed, 89.19% per the fund dashboard.
A19: NIC Otjomuise Ext 10 (Erf 5221) | B19: 17 | C19: Erf 5221, Otjomuise Ext 10, Windhoek | D19: 17 | E19: 17 | F19: 1 | G19: =IF(ISNUMBER(D19),B19-D19,"") -> 0 | H19: Completed — facility redeemed Apr-23 | I19: Contract Parameters D20 — 17 sectional title units. B122 flags units sold as not evidenced.
A20: Sub-total — other projects | B20: =SUM(B15:B19) -> 366 | D20: =SUM(#REF!) -> #REF! | E20: =SUM(#REF!) -> #REF! | G20: =B20-D20 -> #REF!
A21: C. PIPELINE PROJECTS
A22: Ongwediva Town Council | B22: 208 | G22: =IF(ISNUMBER(D22),B22-D22,"") | I22: Kahf Projects Update
A23: Karibib Town Council | B23: 659 | G23: =IF(ISNUMBER(D23),B23-D23,"") | I23: Kahf Projects Update
A24: Goreangab - Waterfront | B24: 815 | G24: =IF(ISNUMBER(D24),B24-D24,"") | I24: Kahf Projects Update
A25: Portion 156 Rundu (Kaisosi Ext 17) | B25: 309 | G25: =IF(ISNUMBER(D25),B25-D25,"") | I25: Kahf Projects Update
A26: Karibi - Nasunga | B26: 84 | G26: =IF(ISNUMBER(D26),B26-D26,"") | I26: Kahf Projects Update
A27: Universitas (Unam) Afrideca | B27: 722 | G27: =IF(ISNUMBER(D27),B27-D27,"")
A28: Auas View | B28: 85
A29: Abigail | B29: 2201
A36: Sub-total — other projects | B36: =SUM(B22:B29) -> 5083 | D36: =SUM(D15:D19) -> 200 | E36: =SUM(E15:E19) -> 70 | G36: =B36-D36 -> 4883
A37: PORTFOLIO TOTAL | B37: =B12+B20+B36 -> 6019 | D37: =D12+D36 -> 200 | E37: =E12+E36 -> 86 | G37: =B37-D37 -> 5819
A39: Blue = hardcoded planned units supplied by the user. Green = figure read from the project model. Black = formula.
A40: Variances against the hardcoded plan, for the record: Mondesa Palms — the model covers Erf 4420 (40 units) only, and the KAHF Projects schedule shows 131, not 134. The Ridge — the KAHF Projects schedule shows 40 units, not 38. PAM Tree, Mango Cove, C-Breeze and Tama agree with the schedule.
A41: Erf 1470 Khomasdal carries three unit counts in one workbook (93 built, 255 to be constructed, 229 housing units, 135 across 6 erven). Treat the delivery number as unaudited until the developer confirms.

Sheet 4. Monthly Cash Flows
A1: SHEET 4 — CONSOLIDATED MONTHLY CASH FLOWS
A2: Live tracking ledger. Every cell is a SUMIFS over the Ledger tab, so adding a dated row on Ledger updates this sheet, Sheet 2 and Sheet 1 automatically. Deployments negative, distributions positive. N$ (NAD).
A4: Month | B4: Fund drawdowns | C4: Fund distributions | D4: Net movement | E4: Cumulative net position | F4: Erf 1470 Khomasdal | G4: Dunescape Villas (Erf 5159) | H4: PAM Tree (Erf 5758) | I4: Turnstone Villas (Erf 8939) | J4: Lithon Nkurenkuru Ext 2 | K4: Mondesa Palms | L4: The Ridge — Rocky Crest Ext 4 | M4: Mango Cove (Otjomuise Ext 10) | N4: C-Breeze Heights | O4: Tama Estates | P4: Duma Tau — Kronlein | Q4: LIH Nkurenkuru Ph 1 | R4: NIC Otjomuise Ext 10 (Erf 5221) | S4: Heavens Ark — Otjomuise
A5: 43040 | B5: =SUMIFS(Ledger!$D$5:$D$109,Ledger!$F$5:$F$109,$A5) -> -47700000 | C5: =SUMIFS(Ledger!$E$5:$E$109,Ledger!$F$5:$F$109,$A5) -> 0 | D5: =B5+C5 -> -47700000 | E5: =D5 -> -47700000 | F5: =SUMIFS(Ledger!$C$5:$C$109,Ledger!$F$5:$F$109,$A5,Ledger!$B$5:$B$109,"Erf 1470 Khomasdal") -> 0 | G5: =SUMIFS(Ledger!$C$5:$C$109,Ledger!$F$5:$F$109,$A5,Ledger!$B$5:$B$109,"Dunescape Villas (Erf 5159)") -> 0 | H5: =SUMIFS(Ledger!$C$5:$C$109,Ledger!$F$5:$F$109,$A5,Ledger!$B$5:$B$109,"PAM Tree (Erf 5758)") -> 0 | I5: =SUMIFS(Ledger!$C$5:$C$109,Ledger!$F$5:$F$109,$A5,Ledger!$B$5:$B$109,"Turnstone Villas (Erf 8939)") -> 0 | J5: =SUMIFS(Ledger!$C$5:$C$109,Ledger!$F$5:$F$109,$A5,Ledger!$B$5:$B$109,"Lithon Nkurenkuru Ext 2") -> 0 | K5: =SUMIFS(Ledger!$C$5:$C$109,Ledger!$F$5:$F$109,$A5,Ledger!$B$5:$B$109,"Mondesa Palms") -> 0 | L5: =SUMIFS(Ledger!$C$5:$C$109,Ledger!$F$5:$F$109,$A5,Ledger!$B$5:$B$109,"The Ridge — Rocky Crest Ext 4") -> 0 | M5: =SUMIFS(Ledger!$C$5:$C$109,Ledger!$F$5:$F$109,$A5,Ledger!$B$5:$B$109,"Mango Cove (Otjomuise Ext 10)") -> 0 | N5: =SUMIFS(Ledger!$C$5:$C$109,Ledger!$F$5:$F$109,$A5,Ledger!$B$5:$B$109,"C-Breeze Heights") -> 0 | O5: =SUMIFS(Ledger!$C$5:$C$109,Ledger!$F$5:$F$109,$A5,Ledger!$B$5:$B$109,"Tama Estates") -> 0 | P5: =SUMIFS(Ledger!$C$5:$C$109,Ledger!$F$5:$F$109,$A5,Ledger!$B$5:$B$109,"Duma Tau — Kronlein") -> 0 | Q5: =SUMIFS(Ledger!$C$5:$C$109,Ledger!$F$5:$F$109,$A5,Ledger!$B$5:$B$109,"LIH Nkurenkuru Ph 1") -> 0 | R5: =SUMIFS(Ledger!$C$5:$C$109,Ledger!$F$5:$F$109,$A5,Ledger!$B$5:$B$109,"NIC Otjomuise Ext 10 (Erf 5221)") -> 0 | S5: =SUMIFS(Ledger!$C$5:$C$109,Ledger!$F$5:$F$109,$A5,Ledger!$B$5:$B$109,"Heavens Ark — Otjomuise") -> 0
A6: 43160 | B6: =SUMIFS(Ledger!$D$5:$D$109,Ledger!$F$5:$F$109,$A6) -> -22000000 | C6: =SUMIFS(Ledger!$E$5:$E$109,Ledger!$F$5:$F$109,$A6) -> 0 | D6: =B6+C6 -> -22000000 | E6: =D6 -> -22000000 | F6: =SUMIFS(Ledger!$C$5:$C$109,Ledger!$F$5:$F$109,$A6,Ledger!$B$5:$B$109,"Erf 1470 Khomasdal") -> 0 | G6: =SUMIFS(Ledger!$C$5:$C$109,Ledger!$F$5:$F$109,$A6,Ledger!$B$5:$B$109,"Dunescape Villas (Erf 5159)") -> 0 | H6: =SUMIFS(Ledger!$C$5:$C$109,Ledger!$F$5:$F$109,$A6,Ledger!$B$5:$B$109,"PAM Tree (Erf 5758)") -> 0 | I6: =SUMIFS(Ledger!$C$5:$C$109,Ledger!$F$5:$F$109,$A6,Ledger!$B$5:$B$109,"Turnstone Villas (Erf 8939)") -> 0 | J6: =SUMIFS(Ledger!$C$5:$C$109,Ledger!$F$5:$F$109,$A6,Ledger!$B$5:$B$109,"Lithon Nkurenkuru Ext 2") -> 0 | K6: =SUMIFS(Ledger!$C$5:$C$109,Ledger!$F$5:$F$109,$A6,Ledger!$B$5:$B$109,"Mondesa Palms") -> 0 | L6: =SUMIFS(Ledger!$C$5:$C$109,Ledger!$F$5:$F$109,$A6,Ledger!$B$5:$B$109,"The Ridge — Rocky Crest Ext 4") -> 0 | M6: =SUMIFS(Ledger!$C$5:$C$109,Ledger!$F$5:$F$109,$A6,Ledger!$B$5:$B$109,"Mango Cove (Otjomuise Ext 10)") -> 0 | N6: =SUMIFS(Ledger!$C$5:$C$109,Ledger!$F$5:$F$109,$A6,Ledger!$B$5:$B$109,"C-Breeze Heights") -> 0 | O6: =SUMIFS(Ledger!$C$5:$C$109,Ledger!$F$5:$F$109,$A6,Ledger!$B$5:$B$109,"Tama Estates") -> 0 | P6: =SUMIFS(Ledger!$C$5:$C$109,Ledger!$F$5:$F$109,$A6,Ledger!$B$5:$B$109,"Duma Tau — Kronlein") -> -22000000 | Q6: =SUMIFS(Ledger!$C$5:$C$109,Ledger!$F$5:$F$109,$A6,Ledger!$B$5:$B$109,"LIH Nkurenkuru Ph 1") -> 0 | R6: =SUMIFS(Ledger!$C$5:$C$109,Ledger!$F$5:$F$109,$A6,Ledger!$B$5:$B$109,"NIC Otjomuise Ext 10 (Erf 5221)") -> 0 | S6: =SUMIFS(Ledger!$C$5:$C$109,Ledger!$F$5:$F$109,$A6,Ledger!$B$5:$B$109,"Heavens Ark — Otjomuise") -> 0
A7: 43191 | B7: =SUMIFS(Ledger!$D$5:$D$109,Ledger!$F$5:$F$109,$A7) -> -10000000 | C7: =SUMIFS(Ledger!$E$5:$E$109,Ledger!$F$5:$F$109,$A7) -> 0 | D7: =B7+C7 -> -10000000 | E7: =D7 -> -10000000 | F7: =SUMIFS(Ledger!$C$5:$C$109,Ledger!$F$5:$F$109,$A7,Ledger!$B$5:$B$109,"Erf 1470 Khomasdal") -> 0 | G7: =SUMIFS(Ledger!$C$5:$C$109,Ledger!$F$5:$F$109,$A7,Ledger!$B$5:$B$109,"Dunescape Villas (Erf 5159)") -> 0 | H7: =SUMIFS(Ledger!$C$5:$C$109,Ledger!$F$5:$F$109,$A7,Ledger!$B$5:$B$109,"PAM Tree (Erf 5758)") -> 0 | I7: =SUMIFS(Ledger!$C$5:$C$109,Ledger!$F$5:$F$109,$A7,Ledger!$B$5:$B$109,"Turnstone Villas (Erf 8939)") -> 0 | J7: =SUMIFS(Ledger!$C$5:$C$109,Ledger!$F$5:$F$109,$A7,Ledger!$B$5:$B$109,"Lithon Nkurenkuru Ext 2") -> 0 | K7: =SUMIFS(Ledger!$C$5:$C$109,Ledger!$F$5:$F$109,$A7,Ledger!$B$5:$B$109,"Mondesa Palms") -> 0 | L7: =SUMIFS(Ledger!$C$5:$C$109,Ledger!$F$5:$F$109,$A7,Ledger!$B$5:$B$109,"The Ridge — Rocky Crest Ext 4") -> 0 | M7: =SUMIFS(Ledger!$C$5:$C$109,Ledger!$F$5:$F$109,$A7,Ledger!$B$5:$B$109,"Mango Cove (Otjomuise Ext 10)") -> 0 | N7: =SUMIFS(Ledger!$C$5:$C$109,Ledger!$F$5:$F$109,$A7,Ledger!$B$5:$B$109,"C-Breeze Heights") -> 0 | O7: =SUMIFS(Ledger!$C$5:$C$109,Ledger!$F$5:$F$109,$A7,Ledger!$B$5:$B$109,"Tama Estates") -> 0 | P7: =SUMIFS(Ledger!$C$5:$C$109,Ledger!$F$5:$F$109,$A7,Ledger!$B$5:$B$109,"Duma Tau — Kronlein") -> 0 | Q7: =SUMIFS(Ledger!$C$5:$C$109,Ledger!$F$5:$F$109,$A7,Ledger!$B$5:$B$109,"LIH Nkurenkuru Ph 1") -> 0 | R7: =SUMIFS(Ledger!$C$5:$C$109,Ledger!$F$5:$F$109,$A7,Ledger!$B$5:$B$109,"NIC Otjomuise Ext 10 (Erf 5221)") -> 0 | S7: =SUMIFS(Ledger!$C$5:$C$109,Ledger!$F$5:$F$109,$A7,Ledger!$B$5:$B$109,"Heavens Ark — Otjomuise") -> 0
A8: 43252 | B8: =SUMIFS(Ledger!$D$5:$D$109,Ledger!$F$5:$F$109,$A8) -> -700000 | C8: =SUMIFS(Ledger!$E$5:$E$109,Ledger!$F$5:$F$109,$A8) -> 0 | D8: =B8+C8 -> -700000 | E8: =D8 -> -700000 | F8: =SUMIFS(Ledger!$C$5:$C$109,Ledger!$F$5:$F$109,$A8,Ledger!$B$5:$B$109,"Erf 1470 Khomasdal") -> 0 | G8: =SUMIFS(Ledger!$C$5:$C$109,Ledger!$F$5:$F$109,$A8,Ledger!$B$5:$B$109,"Dunescape Villas (Erf 5159)") -> 0 | H8: =SUMIFS(Ledger!$C$5:$C$109,Ledger!$F$5:$F$109,$A8,Ledger!$B$5:$B$109,"PAM Tree (Erf 5758)") -> 0 | I8: =SUMIFS(Ledger!$C$5:$C$109,Ledger!$F$5:$F$109,$A8,Ledger!$B$5:$B$109,"Turnstone Villas (Erf 8939)") -> 0 | J8: =SUMIFS(Ledger!$C$5:$C$109,Ledger!$F$5:$F$109,$A8,Ledger!$B$5:$B$109,"Lithon Nkurenkuru Ext 2") -> 0 | K8: =SUMIFS(Ledger!$C$5:$C$109,Ledger!$F$5:$F$109,$A8,Ledger!$B$5:$B$109,"Mondesa Palms") -> 0 | L8: =SUMIFS(Ledger!$C$5:$C$109,Ledger!$F$5:$F$109,$A8,Ledger!$B$5:$B$109,"The Ridge — Rocky Crest Ext 4") -> 0 | M8: =SUMIFS(Ledger!$C$5:$C$109,Ledger!$F$5:$F$109,$A8,Ledger!$B$5:$B$109,"Mango Cove (Otjomuise Ext 10)") -> 0 | N8: =SUMIFS(Ledger!$C$5:$C$109,Ledger!$F$5:$F$109,$A8,Ledger!$B$5:$B$109,"C-Breeze Heights") -> 0 | O8: =SUMIFS(Ledger!$C$5:$C$109,Ledger!$F$5:$F$109,$A8,Ledger!$B$5:$B$109,"Tama Estates") -> 0 | P8: =SUMIFS(Ledger!$C$5:$C$109,Ledger!$F$5:$F$109,$A8,Ledger!$B$5:$B$109,"Duma Tau — Kronlein") -> 0 | Q8: =SUMIFS(Ledger!$C$5:$C$109,Ledger!$F$5:$F$109,$A8,Ledger!$B$5:$B$109,"LIH Nkurenkuru Ph 1") -> 0 | R8: =SUMIFS(Ledger!$C$5:$C$109,Ledger!$F$5:$F$109,$A8,Ledger!$B$5:$B$109,"NIC Otjomuise Ext 10 (Erf 5221)") -> 0 | S8: =SUMIFS(Ledger!$C$5:$C$109,Ledger!$F$5:$F$109,$A8,Ledger!$B$5:$B$109,"Heavens Ark — Otjomuise") -> 0
A9: 43282 | B9: =SUMIFS(Ledger!$D$5:$D$109,Ledger!$F$5:$F$109,$A9) -> -4300000 | C9: =SUMIFS(Ledger!$E$5:$E$109,Ledger!$F$5:$F$109,$A9) -> 0 | D9: =B9+C9 -> -4300000 | E9: =D9 -> -4300000 | F9: =SUMIFS(Ledger!$C$5:$C$109,Ledger!$F$5:$F$109,$A9,Ledger!$B$5:$B$109,"Erf 1470 Khomasdal") -> 0 | G9: =SUMIFS(Ledger!$C$5:$C$109,Ledger!$F$5:$F$109,$A9,Ledger!$B$5:$B$109,"Dunescape Villas (Erf 5159)") -> 0 | H9: =SUMIFS(Ledger!$C$5:$C$109,Ledger!$F$5:$F$109,$A9,Ledger!$B$5:$B$109,"PAM Tree (Erf 5758)") -> 0 | I9: =SUMIFS(Ledger!$C$5:$C$109,Ledger!$F$5:$F$109,$A9,Ledger!$B$5:$B$109,"Turnstone Villas (Erf 8939)") -> 0 | J9: =SUMIFS(Ledger!$C$5:$C$109,Ledger!$F$5:$F$109,$A9,Ledger!$B$5:$B$109,"Lithon Nkurenkuru Ext 2") -> 0 | K9: =SUMIFS(Ledger!$C$5:$C$109,Ledger!$F$5:$F$109,$A9,Ledger!$B$5:$B$109,"Mondesa Palms") -> 0 | L9: =SUMIFS(Ledger!$C$5:$C$109,Ledger!$F$5:$F$109,$A9,Ledger!$B$5:$B$109,"The Ridge — Rocky Crest Ext 4") -> 0 | M9: =SUMIFS(Ledger!$C$5:$C$109,Ledger!$F$5:$F$109,$A9,Ledger!$B$5:$B$109,"Mango Cove (Otjomuise Ext 10)") -> 0 | N9: =SUMIFS(Ledger!$C$5:$C$109,Ledger!$F$5:$F$109,$A9,Ledger!$B$5:$B$109,"C-Breeze Heights") -> 0 | O9: =SUMIFS(Ledger!$C$5:$C$109,Ledger!$F$5:$F$109,$A9,Ledger!$B$5:$B$109,"Tama Estates") -> 0 | P9: =SUMIFS(Ledger!$C$5:$C$109,Ledger!$F$5:$F$109,$A9,Ledger!$B$5:$B$109,"Duma Tau — Kronlein") -> 0 | Q9: =SUMIFS(Ledger!$C$5:$C$109,Ledger!$F$5:$F$109,$A9,Ledger!$B$5:$B$109,"LIH Nkurenkuru Ph 1") -> 0 | R9: =SUMIFS(Ledger!$C$5:$C$109,Ledger!$F$5:$F$109,$A9,Ledger!$B$5:$B$109,"NIC Otjomuise Ext 10 (Erf 5221)") -> 0 | S9: =SUMIFS(Ledger!$C$5:$C$109,Ledger!$F$5:$F$109,$A9,Ledger!$B$5:$B$109,"Heavens Ark — Otjomuise") -> 0
A10: 43313 | B10: =SUMIFS(Ledger!$D$5:$D$109,Ledger!$F$5:$F$109,$A10) -> -11000000 | C10: =SUMIFS(Ledger!$E$5:$E$109,Ledger!$F$5:$F$109,$A10) -> 0 | D10: =B10+C10 -> -11000000 | E10: =D10 -> -11000000 | F10: =SUMIFS(Ledger!$C$5:$C$109,Ledger!$F$5:$F$109,$A10,Ledger!$B$5:$B$109,"Erf 1470 Khomasdal") -> 0 | G10: =SUMIFS(Ledger!$C$5:$C$109,Ledger!$F$5:$F$109,$A10,Ledger!$B$5:$B$109,"Dunescape Villas (Erf 5159)") -> 0 | H10: =SUMIFS(Ledger!$C$5:$C$109,Ledger!$F$5:$F$109,$A10,Ledger!$B$5:$B$109,"PAM Tree (Erf 5758)") -> 0 | I10: =SUMIFS(Ledger!$C$5:$C$109,Ledger!$F$5:$F$109,$A10,Ledger!$B$5:$B$109,"Turnstone Villas (Erf 8939)") -> 0 | J10: =SUMIFS(Ledger!$C$5:$C$109,Ledger!$F$5:$F$109,$A10,Ledger!$B$5:$B$109,"Lithon Nkurenkuru Ext 2") -> 0 | K10: =SUMIFS(Ledger!$C$5:$C$109,Ledger!$F$5:$F$109,$A10,Ledger!$B$5:$B$109,"Mondesa Palms") -> 0 | L10: =SUMIFS(Ledger!$C$5:$C$109,Ledger!$F$5:$F$109,$A10,Ledger!$B$5:$B$109,"The Ridge — Rocky Crest Ext 4") -> 0 | M10: =SUMIFS(Ledger!$C$5:$C$109,Ledger!$F$5:$F$109,$A10,Ledger!$B$5:$B$109,"Mango Cove (Otjomuise Ext 10)") -> 0 | N10: =SUMIFS(Ledger!$C$5:$C$109,Ledger!$F$5:$F$109,$A10,Ledger!$B$5:$B$109,"C-Breeze Heights") -> 0 | O10: =SUMIFS(Ledger!$C$5:$C$109,Ledger!$F$5:$F$109,$A10,Ledger!$B$5:$B$109,"Tama Estates") -> 0 | P10: =SUMIFS(Ledger!$C$5:$C$109,Ledger!$F$5:$F$109,$A10,Ledger!$B$5:$B$109,"Duma Tau — Kronlein") -> -6000000 | Q10: =SUMIFS(Ledger!$C$5:$C$109,Ledger!$F$5:$F$109,$A10,Ledger!$B$5:$B$109,"LIH Nkurenkuru Ph 1") -> 0 | R10: =SUMIFS(Ledger!$C$5:$C$109,Ledger!$F$5:$F$109,$A10,Ledger!$B$5:$B$109,"NIC Otjomuise Ext 10 (Erf 5221)") -> 0 | S10: =SUMIFS(Ledger!$C$5:$C$109,Ledger!$F$5:$F$109,$A10,Ledger!$B$5:$B$109,"Heavens Ark — Otjomuise") -> 0
A11: 43344 | B11: =SUMIFS(Ledger!$D$5:$D$109,Ledger!$F$5:$F$109,$A11) -> -2500000 | C11: =SUMIFS(Ledger!$E$5:$E$109,Ledger!$F$5:$F$109,$A11) -> 1302000 | D11: =B11+C11 -> -1198000 | E11: =D11 -> -1198000 | F11: =SUMIFS(Ledger!$C$5:$C$109,Ledger!$F$5:$F$109,$A11,Ledger!$B$5:$B$109,"Erf 1470 Khomasdal") -> 0 | G11: =SUMIFS(Ledger!$C$5:$C$109,Ledger!$F$5:$F$109,$A11,Ledger!$B$5:$B$109,"Dunescape Villas (Erf 5159)") -> 0 | H11: =SUMIFS(Ledger!$C$5:$C$109,Ledger!$F$5:$F$109,$A11,Ledger!$B$5:$B$109,"PAM Tree (Erf 5758)") -> 0 | I11: =SUMIFS(Ledger!$C$5:$C$109,Ledger!$F$5:$F$109,$A11,Ledger!$B$5:$B$109,"Turnstone Villas (Erf 8939)") -> 0 | J11: =SUMIFS(Ledger!$C$5:$C$109,Ledger!$F$5:$F$109,$A11,Ledger!$B$5:$B$109,"Lithon Nkurenkuru Ext 2") -> 0 | K11: =SUMIFS(Ledger!$C$5:$C$109,Ledger!$F$5:$F$109,$A11,Ledger!$B$5:$B$109,"Mondesa Palms") -> 0 | L11: =SUMIFS(Ledger!$C$5:$C$109,Ledger!$F$5:$F$109,$A11,Ledger!$B$5:$B$109,"The Ridge — Rocky Crest Ext 4") -> 0 | M11: =SUMIFS(Ledger!$C$5:$C$109,Ledger!$F$5:$F$109,$A11,Ledger!$B$5:$B$109,"Mango Cove (Otjomuise Ext 10)") -> 0 | N11: =SUMIFS(Ledger!$C$5:$C$109,Ledger!$F$5:$F$109,$A11,Ledger!$B$5:$B$109,"C-Breeze Heights") -> 0 | O11: =SUMIFS(Ledger!$C$5:$C$109,Ledger!$F$5:$F$109,$A11,Ledger!$B$5:$B$109,"Tama Estates") -> 0 | P11: =SUMIFS(Ledger!$C$5:$C$109,Ledger!$F$5:$F$109,$A11,Ledger!$B$5:$B$109,"Duma Tau — Kronlein") -> 1302000 | Q11: =SUMIFS(Ledger!$C$5:$C$109,Ledger!$F$5:$F$109,$A11,Ledger!$B$5:$B$109,"LIH Nkurenkuru Ph 1") -> 0 | R11: =SUMIFS(Ledger!$C$5:$C$109,Ledger!$F$5:$F$109,$A11,Ledger!$B$5:$B$109,"NIC Otjomuise Ext 10 (Erf 5221)") -> 0 | S11: =SUMIFS(Ledger!$C$5:$C$109,Ledger!$F$5:$F$109,$A11,Ledger!$B$5:$B$109,"Heavens Ark — Otjomuise") -> 0
A12: 43374 | B12: =SUMIFS(Ledger!$D$5:$D$109,Ledger!$F$5:$F$109,$A12) -> -10000000 | C12: =SUMIFS(Ledger!$E$5:$E$109,Ledger!$F$5:$F$109,$A12) -> 0 | D12: =B12+C12 -> -10000000 | E12: =D12 -> -10000000 | F12: =SUMIFS(Ledger!$C$5:$C$109,Ledger!$F$5:$F$109,$A12,Ledger!$B$5:$B$109,"Erf 1470 Khomasdal") -> 0 | G12: =SUMIFS(Ledger!$C$5:$C$109,Ledger!$F$5:$F$109,$A12,Ledger!$B$5:$B$109,"Dunescape Villas (Erf 5159)") -> 0 | H12: =SUMIFS(Ledger!$C$5:$C$109,Ledger!$F$5:$F$109,$A12,Ledger!$B$5:$B$109,"PAM Tree (Erf 5758)") -> 0 | I12: =SUMIFS(Ledger!$C$5:$C$109,Ledger!$F$5:$F$109,$A12,Ledger!$B$5:$B$109,"Turnstone Villas (Erf 8939)") -> 0 | J12: =SUMIFS(Ledger!$C$5:$C$109,Ledger!$F$5:$F$109,$A12,Ledger!$B$5:$B$109,"Lithon Nkurenkuru Ext 2") -> 0 | K12: =SUMIFS(Ledger!$C$5:$C$109,Ledger!$F$5:$F$109,$A12,Ledger!$B$5:$B$109,"Mondesa Palms") -> 0 | L12: =SUMIFS(Ledger!$C$5:$C$109,Ledger!$F$5:$F$109,$A12,Ledger!$B$5:$B$109,"The Ridge — Rocky Crest Ext 4") -> 0 | M12: =SUMIFS(Ledger!$C$5:$C$109,Ledger!$F$5:$F$109,$A12,Ledger!$B$5:$B$109,"Mango Cove (Otjomuise Ext 10)") -> 0 | N12: =SUMIFS(Ledger!$C$5:$C$109,Ledger!$F$5:$F$109,$A12,Ledger!$B$5:$B$109,"C-Breeze Heights") -> 0 | O12: =SUMIFS(Ledger!$C$5:$C$109,Ledger!$F$5:$F$109,$A12,Ledger!$B$5:$B$109,"Tama Estates") -> 0 | P12: =SUMIFS(Ledger!$C$5:$C$109,Ledger!$F$5:$F$109,$A12,Ledger!$B$5:$B$109,"Duma Tau — Kronlein") -> 0 | Q12: =SUMIFS(Ledger!$C$5:$C$109,Ledger!$F$5:$F$109,$A12,Ledger!$B$5:$B$109,"LIH Nkurenkuru Ph 1") -> 0 | R12: =SUMIFS(Ledger!$C$5:$C$109,Ledger!$F$5:$F$109,$A12,Ledger!$B$5:$B$109,"NIC Otjomuise Ext 10 (Erf 5221)") -> 0 | S12: =SUMIFS(Ledger!$C$5:$C$109,Ledger!$F$5:$F$109,$A12,Ledger!$B$5:$B$109,"Heavens Ark — Otjomuise") -> 0
A13: 43405 | B13: =SUMIFS(Ledger!$D$5:$D$109,Ledger!$F$5:$F$109,$A13) -> -11600000 | C13: =SUMIFS(Ledger!$E$5:$E$109,Ledger!$F$5:$F$109,$A13) -> 0 | D13: =B13+C13 -> -11600000 | E13: =D13 -> -11600000 | F13: =SUMIFS(Ledger!$C$5:$C$109,Ledger!$F$5:$F$109,$A13,Ledger!$B$5:$B$109,"Erf 1470 Khomasdal") -> 0 | G13: =SUMIFS(Ledger!$C$5:$C$109,Ledger!$F$5:$F$109,$A13,Ledger!$B$5:$B$109,"Dunescape Villas (Erf 5159)") -> 0 | H13: =SUMIFS(Ledger!$C$5:$C$109,Ledger!$F$5:$F$109,$A13,Ledger!$B$5:$B$109,"PAM Tree (Erf 5758)") -> 0 | I13: =SUMIFS(Ledger!$C$5:$C$109,Ledger!$F$5:$F$109,$A13,Ledger!$B$5:$B$109,"Turnstone Villas (Erf 8939)") -> 0 | J13: =SUMIFS(Ledger!$C$5:$C$109,Ledger!$F$5:$F$109,$A13,Ledger!$B$5:$B$109,"Lithon Nkurenkuru Ext 2") -> 0 | K13: =SUMIFS(Ledger!$C$5:$C$109,Ledger!$F$5:$F$109,$A13,Ledger!$B$5:$B$109,"Mondesa Palms") -> 0 | L13: =SUMIFS(Ledger!$C$5:$C$109,Ledger!$F$5:$F$109,$A13,Ledger!$B$5:$B$109,"The Ridge — Rocky Crest Ext 4") -> 0 | M13: =SUMIFS(Ledger!$C$5:$C$109,Ledger!$F$5:$F$109,$A13,Ledger!$B$5:$B$109,"Mango Cove (Otjomuise Ext 10)") -> 0 | N13: =SUMIFS(Ledger!$C$5:$C$109,Ledger!$F$5:$F$109,$A13,Ledger!$B$5:$B$109,"C-Breeze Heights") -> 0 | O13: =SUMIFS(Ledger!$C$5:$C$109,Ledger!$F$5:$F$109,$A13,Ledger!$B$5:$B$109,"Tama Estates") -> 0 | P13: =SUMIFS(Ledger!$C$5:$C$109,Ledger!$F$5:$F$109,$A13,Ledger!$B$5:$B$109,"Duma Tau — Kronlein") -> 0 | Q13: =SUMIFS(Ledger!$C$5:$C$109,Ledger!$F$5:$F$109,$A13,Ledger!$B$5:$B$109,"LIH Nkurenkuru Ph 1") -> 0 | R13: =SUMIFS(Ledger!$C$5:$C$109,Ledger!$F$5:$F$109,$A13,Ledger!$B$5:$B$109,"NIC Otjomuise Ext 10 (Erf 5221)") -> 0 | S13: =SUMIFS(Ledger!$C$5:$C$109,Ledger!$F$5:$F$109,$A13,Ledger!$B$5:$B$109,"Heavens Ark — Otjomuise") -> 0
A14: 43435 | B14: =SUMIFS(Ledger!$D$5:$D$109,Ledger!$F$5:$F$109,$A14) -> 0 | C14: =SUMIFS(Ledger!$E$5:$E$109,Ledger!$F$5:$F$109,$A14) -> 10443745 | D14: =B14+C14 -> 10443745 | E14: =D14 -> 10443745 | F14: =SUMIFS(Ledger!$C$5:$C$109,Ledger!$F$5:$F$109,$A14,Ledger!$B$5:$B$109,"Erf 1470 Khomasdal") -> 0 | G14: =SUMIFS(Ledger!$C$5:$C$109,Ledger!$F$5:$F$109,$A14,Ledger!$B$5:$B$109,"Dunescape Villas (Erf 5159)") -> 0 | H14: =SUMIFS(Ledger!$C$5:$C$109,Ledger!$F$5:$F$109,$A14,Ledger!$B$5:$B$109,"PAM Tree (Erf 5758)") -> 0 | I14: =SUMIFS(Ledger!$C$5:$C$109,Ledger!$F$5:$F$109,$A14,Ledger!$B$5:$B$109,"Turnstone Villas (Erf 8939)") -> 0 | J14: =SUMIFS(Ledger!$C$5:$C$109,Ledger!$F$5:$F$109,$A14,Ledger!$B$5:$B$109,"Lithon Nkurenkuru Ext 2") -> 0 | K14: =SUMIFS(Ledger!$C$5:$C$109,Ledger!$F$5:$F$109,$A14,Ledger!$B$5:$B$109,"Mondesa Palms") -> 0 | L14: =SUMIFS(Ledger!$C$5:$C$109,Ledger!$F$5:$F$109,$A14,Ledger!$B$5:$B$109,"The Ridge — Rocky Crest Ext 4") -> 0 | M14: =SUMIFS(Ledger!$C$5:$C$109,Ledger!$F$5:$F$109,$A14,Ledger!$B$5:$B$109,"Mango Cove (Otjomuise Ext 10)") -> 0 | N14: =SUMIFS(Ledger!$C$5:$C$109,Ledger!$F$5:$F$109,$A14,Ledger!$B$5:$B$109,"C-Breeze Heights") -> 0 | O14: =SUMIFS(Ledger!$C$5:$C$109,Ledger!$F$5:$F$109,$A14,Ledger!$B$5:$B$109,"Tama Estates") -> 0 | P14: =SUMIFS(Ledger!$C$5:$C$109,Ledger!$F$5:$F$109,$A14,Ledger!$B$5:$B$109,"Duma Tau — Kronlein") -> 10443745 | Q14: =SUMIFS(Ledger!$C$5:$C$109,Ledger!$F$5:$F$109,$A14,Ledger!$B$5:$B$109,"LIH Nkurenkuru Ph 1") -> 0 | R14: =SUMIFS(Ledger!$C$5:$C$109,Ledger!$F$5:$F$109,$A14,Ledger!$B$5:$B$109,"NIC Otjomuise Ext 10 (Erf 5221)") -> 0 | S14: =SUMIFS(Ledger!$C$5:$C$109,Ledger!$F$5:$F$109,$A14,Ledger!$B$5:$B$109,"Heavens Ark — Otjomuise") -> 0
A15: 43466 | B15: =SUMIFS(Ledger!$D$5:$D$109,Ledger!$F$5:$F$109,$A15) -> -12450000 | C15: =SUMIFS(Ledger!$E$5:$E$109,Ledger!$F$5:$F$109,$A15) -> 4425225 | D15: =B15+C15 -> -8024775 | E15: =D15 -> -8024775 | F15: =SUMIFS(Ledger!$C$5:$C$109,Ledger!$F$5:$F$109,$A15,Ledger!$B$5:$B$109,"Erf 1470 Khomasdal") -> 0 | G15: =SUMIFS(Ledger!$C$5:$C$109,Ledger!$F$5:$F$109,$A15,Ledger!$B$5:$B$109,"Dunescape Villas (Erf 5159)") -> 0 | H15: =SUMIFS(Ledger!$C$5:$C$109,Ledger!$F$5:$F$109,$A15,Ledger!$B$5:$B$109,"PAM Tree (Erf 5758)") -> 0 | I15: =SUMIFS(Ledger!$C$5:$C$109,Ledger!$F$5:$F$109,$A15,Ledger!$B$5:$B$109,"Turnstone Villas (Erf 8939)") -> 0 | J15: =SUMIFS(Ledger!$C$5:$C$109,Ledger!$F$5:$F$109,$A15,Ledger!$B$5:$B$109,"Lithon Nkurenkuru Ext 2") -> 0 | K15: =SUMIFS(Ledger!$C$5:$C$109,Ledger!$F$5:$F$109,$A15,Ledger!$B$5:$B$109,"Mondesa Palms") -> 0 | L15: =SUMIFS(Ledger!$C$5:$C$109,Ledger!$F$5:$F$109,$A15,Ledger!$B$5:$B$109,"The Ridge — Rocky Crest Ext 4") -> 0 | M15: =SUMIFS(Ledger!$C$5:$C$109,Ledger!$F$5:$F$109,$A15,Ledger!$B$5:$B$109,"Mango Cove (Otjomuise Ext 10)") -> 0 | N15: =SUMIFS(Ledger!$C$5:$C$109,Ledger!$F$5:$F$109,$A15,Ledger!$B$5:$B$109,"C-Breeze Heights") -> 0 | O15: =SUMIFS(Ledger!$C$5:$C$109,Ledger!$F$5:$F$109,$A15,Ledger!$B$5:$B$109,"Tama Estates") -> 0 | P15: =SUMIFS(Ledger!$C$5:$C$109,Ledger!$F$5:$F$109,$A15,Ledger!$B$5:$B$109,"Duma Tau — Kronlein") -> 4425225 | Q15: =SUMIFS(Ledger!$C$5:$C$109,Ledger!$F$5:$F$109,$A15,Ledger!$B$5:$B$109,"LIH Nkurenkuru Ph 1") -> 0 | R15: =SUMIFS(Ledger!$C$5:$C$109,Ledger!$F$5:$F$109,$A15,Ledger!$B$5:$B$109,"NIC Otjomuise Ext 10 (Erf 5221)") -> 0 | S15: =SUMIFS(Ledger!$C$5:$C$109,Ledger!$F$5:$F$109,$A15,Ledger!$B$5:$B$109,"Heavens Ark — Otjomuise") -> 0
A16: 43497 | B16: =SUMIFS(Ledger!$D$5:$D$109,Ledger!$F$5:$F$109,$A16) -> -10400000 | C16: =SUMIFS(Ledger!$E$5:$E$109,Ledger!$F$5:$F$109,$A16) -> 3242310 | D16: =B16+C16 -> -7157690 | E16: =D16 -> -7157690 | F16: =SUMIFS(Ledger!$C$5:$C$109,Ledger!$F$5:$F$109,$A16,Ledger!$B$5:$B$109,"Erf 1470 Khomasdal") -> 0 | G16: =SUMIFS(Ledger!$C$5:$C$109,Ledger!$F$5:$F$109,$A16,Ledger!$B$5:$B$109,"Dunescape Villas (Erf 5159)") -> 0 | H16: =SUMIFS(Ledger!$C$5:$C$109,Ledger!$F$5:$F$109,$A16,Ledger!$B$5:$B$109,"PAM Tree (Erf 5758)") -> 0 | I16: =SUMIFS(Ledger!$C$5:$C$109,Ledger!$F$5:$F$109,$A16,Ledger!$B$5:$B$109,"Turnstone Villas (Erf 8939)") -> 0 | J16: =SUMIFS(Ledger!$C$5:$C$109,Ledger!$F$5:$F$109,$A16,Ledger!$B$5:$B$109,"Lithon Nkurenkuru Ext 2") -> 0 | K16: =SUMIFS(Ledger!$C$5:$C$109,Ledger!$F$5:$F$109,$A16,Ledger!$B$5:$B$109,"Mondesa Palms") -> 0 | L16: =SUMIFS(Ledger!$C$5:$C$109,Ledger!$F$5:$F$109,$A16,Ledger!$B$5:$B$109,"The Ridge — Rocky Crest Ext 4") -> 0 | M16: =SUMIFS(Ledger!$C$5:$C$109,Ledger!$F$5:$F$109,$A16,Ledger!$B$5:$B$109,"Mango Cove (Otjomuise Ext 10)") -> 0 | N16: =SUMIFS(Ledger!$C$5:$C$109,Ledger!$F$5:$F$109,$A16,Ledger!$B$5:$B$109,"C-Breeze Heights") -> 0 | O16: =SUMIFS(Ledger!$C$5:$C$109,Ledger!$F$5:$F$109,$A16,Ledger!$B$5:$B$109,"Tama Estates") -> 0 | P16: =SUMIFS(Ledger!$C$5:$C$109,Ledger!$F$5:$F$109,$A16,Ledger!$B$5:$B$109,"Duma Tau — Kronlein") -> 3242310 | Q16: =SUMIFS(Ledger!$C$5:$C$109,Ledger!$F$5:$F$109,$A16,Ledger!$B$5:$B$109,"LIH Nkurenkuru Ph 1") -> 0 | R16: =SUMIFS(Ledger!$C$5:$C$109,Ledger!$F$5:$F$109,$A16,Ledger!$B$5:$B$109,"NIC Otjomuise Ext 10 (Erf 5221)") -> 0 | S16: =SUMIFS(Ledger!$C$5:$C$109,Ledger!$F$5:$F$109,$A16,Ledger!$B$5:$B$109,"Heavens Ark — Otjomuise") -> 0
... A34: 44531 | B34: =SUMIFS(Ledger!$D$5:$D$109,Ledger!$F$5:$F$109,$A34) -> 0 | C34: =SUMIFS(Ledger!$E$5:$E$109,Ledger!$F$5:$F$109,$A34) -> 4575267.8 | D34: =B34+C34 -> 4575267.8 | E34: =D34 -> 4575267.8 | F34: =SUMIFS(Ledger!$C$5:$C$109,Ledger!$F$5:$F$109,$A34,Ledger!$B$5:$B$109,"Erf 1470 Khomasdal") -> 0 | G34: =SUMIFS(Ledger!$C$5:$C$109,Ledger!$F$5:$F$109,$A34,Ledger!$B$5:$B$109,"Dunescape Villas (Erf 5159)") -> 0 | H34: =SUMIFS(Ledger!$C$5:$C$109,Ledger!$F$5:$F$109,$A34,Ledger!$B$5:$B$109,"PAM Tree (Erf 5758)") -> 0 | I34: =SUMIFS(Ledger!$C$5:$C$109,Ledger!$F$5:$F$109,$A34,Ledger!$B$5:$B$109,"Turnstone Villas (Erf 8939)") -> 0 | J34: =SUMIFS(Ledger!$C$5:$C$109,Ledger!$F$5:$F$109,$A34,Ledger!$B$5:$B$109,"Lithon Nkurenkuru Ext 2") -> 0 | K34: =SUMIFS(Ledger!$C$5:$C$109,Ledger!$F$5:$F$109,$A34,Ledger!$B$5:$B$109,"Mondesa Palms") -> 0 | L34: =SUMIFS(Ledger!$C$5:$C$109,Ledger!$F$5:$F$109,$A34,Ledger!$B$5:$B$109,"The Ridge — Rocky Crest Ext 4") -> 0 | M34: =SUMIFS(Ledger!$C$5:$C$109,Ledger!$F$5:$F$109,$A34,Ledger!$B$5:$B$109,"Mango Cove (Otjomuise Ext 10)") -> 0 | N34: =SUMIFS(Ledger!$C$5:$C$109,Ledger!$F$5:$F$109,$A34,Ledger!$B$5:$B$109,"C-Breeze Heights") -> 0 | O34: =SUMIFS(Ledger!$C$5:$C$109,Ledger!$F$5:$F$109,$A34,Ledger!$B$5:$B$109,"Tama Estates") -> 0 | P34: =SUMIFS(Ledger!$C$5:$C$109,Ledger!$F$5:$F$109,$A34,Ledger!$B$5:$B$109,"Duma Tau — Kronlein") -> 3481490.1 | Q34: =SUMIFS(Ledger!$C$5:$C$109,Ledger!$F$5:$F$109,$A34,Ledger!$B$5:$B$109,"LIH Nkurenkuru Ph 1") -> 0 | R34: =SUMIFS(Ledger!$C$5:$C$109,Ledger!$F$5:$F$109,$A34,Ledger!$B$5:$B$109,"NIC Otjomuise Ext 10 (Erf 5221)") -> 0 | S34: =SUMIFS(Ledger!$C$5:$C$109,Ledger!$F$5:$F$109,$A34,Ledger!$B$5:$B$109,"Heavens Ark — Otjomuise") -> 0
A35: 44682 | B35: =SUMIFS(Ledger!$D$5:$D$109,Ledger!$F$5:$F$109,$A35) -> -5500000 | C35: =SUMIFS(Ledger!$E$5:$E$109,Ledger!$F$5:$F$109,$A35) -> 0 | D35: =B35+C35 -> -5500000 | E35: =E34+D35 -> -924732.24 | F35: =SUMIFS(Ledger!$C$5:$C$109,Ledger!$F$5:$F$109,$A35,Ledger!$B$5:$B$109,"Erf 1470 Khomasdal") -> 0 | G35: =SUMIFS(Ledger!$C$5:$C$109,Ledger!$F$5:$F$109,$A35,Ledger!$B$5:$B$109,"Dunescape Villas (Erf 5159)") -> 0 | H35: =SUMIFS(Ledger!$C$5:$C$109,Ledger!$F$5:$F$109,$A35,Ledger!$B$5:$B$109,"PAM Tree (Erf 5758)") -> 0 | I35: =SUMIFS(Ledger!$C$5:$C$109,Ledger!$F$5:$F$109,$A35,Ledger!$B$5:$B$109,"Turnstone Villas (Erf 8939)") -> 0 | J35: =SUMIFS(Ledger!$C$5:$C$109,Ledger!$F$5:$F$109,$A35,Ledger!$B$5:$B$109,"Lithon Nkurenkuru Ext 2") -> 0 | K35: =SUMIFS(Ledger!$C$5:$C$109,Ledger!$F$5:$F$109,$A35,Ledger!$B$5:$B$109,"Mondesa Palms") -> 0 | L35: =SUMIFS(Ledger!$C$5:$C$109,Ledger!$F$5:$F$109,$A35,Ledger!$B$5:$B$109,"The Ridge — Rocky Crest Ext 4") -> 0 | M35: =SUMIFS(Ledger!$C$5:$C$109,Ledger!$F$5:$F$109,$A35,Ledger!$B$5:$B$109,"Mango Cove (Otjomuise Ext 10)") -> 0 | N35: =SUMIFS(Ledger!$C$5:$C$109,Ledger!$F$5:$F$109,$A35,Ledger!$B$5:$B$109,"C-Breeze Heights") -> 0 | O35: =SUMIFS(Ledger!$C$5:$C$109,Ledger!$F$5:$F$109,$A35,Ledger!$B$5:$B$109,"Tama Estates") -> 0 | P35: =SUMIFS(Ledger!$C$5:$C$109,Ledger!$F$5:$F$109,$A35,Ledger!$B$5:$B$109,"Duma Tau — Kronlein") -> 0 | Q35: =SUMIFS(Ledger!$C$5:$C$109,Ledger!$F$5:$F$109,$A35,Ledger!$B$5:$B$109,"LIH Nkurenkuru Ph 1") -> 0 | R35: =SUMIFS(Ledger!$C$5:$C$109,Ledger!$F$5:$F$109,$A35,Ledger!$B$5:$B$109,"NIC Otjomuise Ext 10 (Erf 5221)") -> 0 | S35: =SUMIFS(Ledger!$C$5:$C$109,Ledger!$F$5:$F$109,$A35,Ledger!$B$5:$B$109,"Heavens Ark — Otjomuise") -> 0
A36: 44774 | B36: =SUMIFS(Ledger!$D$5:$D$109,Ledger!$F$5:$F$109,$A36) -> -7000000 | C36: =SUMIFS(Ledger!$E$5:$E$109,Ledger!$F$5:$F$109,$A36) -> 0 | D36: =B36+C36 -> -7000000 | E36: =D36 -> -7000000 | F36: =SUMIFS(Ledger!$C$5:$C$109,Ledger!$F$5:$F$109,$A36,Ledger!$B$5:$B$109,"Erf 1470 Khomasdal") -> 0 | G36: =SUMIFS(Ledger!$C$5:$C$109,Ledger!$F$5:$F$109,$A36,Ledger!$B$5:$B$109,"Dunescape Villas (Erf 5159)") -> 0 | H36: =SUMIFS(Ledger!$C$5:$C$109,Ledger!$F$5:$F$109,$A36,Ledger!$B$5:$B$109,"PAM Tree (Erf 5758)") -> 0 | I36: =SUMIFS(Ledger!$C$5:$C$109,Ledger!$F$5:$F$109,$A36,Ledger!$B$5:$B$109,"Turnstone Villas (Erf 8939)") -> 0 | J36: =SUMIFS(Ledger!$C$5:$C$109,Ledger!$F$5:$F$109,$A36,Ledger!$B$5:$B$109,"Lithon Nkurenkuru Ext 2") -> 0 | K36: =SUMIFS(Ledger!$C$5:$C$109,Ledger!$F$5:$F$109,$A36,Ledger!$B$5:$B$109,"Mondesa Palms") -> 0 | L36: =SUMIFS(Ledger!$C$5:$C$109,Ledger!$F$5:$F$109,$A36,Ledger!$B$5:$B$109,"The Ridge — Rocky Crest Ext 4") -> 0 | M36: =SUMIFS(Ledger!$C$5:$C$109,Ledger!$F$5:$F$109,$A36,Ledger!$B$5:$B$109,"Mango Cove (Otjomuise Ext 10)") -> 0 | N36: =SUMIFS(Ledger!$C$5:$C$109,Ledger!$F$5:$F$109,$A36,Ledger!$B$5:$B$109,"C-Breeze Heights") -> 0 | O36: =SUMIFS(Ledger!$C$5:$C$109,Ledger!$F$5:$F$109,$A36,Ledger!$B$5:$B$109,"Tama Estates") -> 0 | P36: =SUMIFS(Ledger!$C$5:$C$109,Ledger!$F$5:$F$109,$A36,Ledger!$B$5:$B$109,"Duma Tau — Kronlein") -> 0 | Q36: =SUMIFS(Ledger!$C$5:$C$109,Ledger!$F$5:$F$109,$A36,Ledger!$B$5:$B$109,"LIH Nkurenkuru Ph 1") -> 0 | R36: =SUMIFS(Ledger!$C$5:$C$109,Ledger!$F$5:$F$109,$A36,Ledger!$B$5:$B$109,"NIC Otjomuise Ext 10 (Erf 5221)") -> 0 | S36: =SUMIFS(Ledger!$C$5:$C$109,Ledger!$F$5:$F$109,$A36,Ledger!$B$5:$B$109,"Heavens Ark — Otjomuise") -> 0
A37: 44866 | B37: =SUMIFS(Ledger!$D$5:$D$109,Ledger!$F$5:$F$109,$A37) -> 0 | C37: =SUMIFS(Ledger!$E$5:$E$109,Ledger!$F$5:$F$109,$A37) -> 0 | D37: =B37+C37 -> 0 | E37: =D37 -> 0 | F37: =SUMIFS(Ledger!$C$5:$C$109,Ledger!$F$5:$F$109,$A37,Ledger!$B$5:$B$109,"Erf 1470 Khomasdal") -> 0 | G37: =SUMIFS(Ledger!$C$5:$C$109,Ledger!$F$5:$F$109,$A37,Ledger!$B$5:$B$109,"Dunescape Villas (Erf 5159)") -> 0 | H37: =SUMIFS(Ledger!$C$5:$C$109,Ledger!$F$5:$F$109,$A37,Ledger!$B$5:$B$109,"PAM Tree (Erf 5758)") -> 0 | I37: =SUMIFS(Ledger!$C$5:$C$109,Ledger!$F$5:$F$109,$A37,Ledger!$B$5:$B$109,"Turnstone Villas (Erf 8939)") -> 0 | J37: =SUMIFS(Ledger!$C$5:$C$109,Ledger!$F$5:$F$109,$A37,Ledger!$B$5:$B$109,"Lithon Nkurenkuru Ext 2") -> 0 | K37: =SUMIFS(Ledger!$C$5:$C$109,Ledger!$F$5:$F$109,$A37,Ledger!$B$5:$B$109,"Mondesa Palms") -> 0 | L37: =SUMIFS(Ledger!$C$5:$C$109,Ledger!$F$5:$F$109,$A37,Ledger!$B$5:$B$109,"The Ridge — Rocky Crest Ext 4") -> 0 | M37: =SUMIFS(Ledger!$C$5:$C$109,Ledger!$F$5:$F$109,$A37,Ledger!$B$5:$B$109,"Mango Cove (Otjomuise Ext 10)") -> 0 | N37: =SUMIFS(Ledger!$C$5:$C$109,Ledger!$F$5:$F$109,$A37,Ledger!$B$5:$B$109,"C-Breeze Heights") -> 0 | O37: =SUMIFS(Ledger!$C$5:$C$109,Ledger!$F$5:$F$109,$A37,Ledger!$B$5:$B$109,"Tama Estates") -> 0 | P37: =SUMIFS(Ledger!$C$5:$C$109,Ledger!$F$5:$F$109,$A37,Ledger!$B$5:$B$109,"Duma Tau — Kronlein") -> 0 | Q37: =SUMIFS(Ledger!$C$5:$C$109,Ledger!$F$5:$F$109,$A37,Ledger!$B$5:$B$109,"LIH Nkurenkuru Ph 1") -> 0 | R37: =SUMIFS(Ledger!$C$5:$C$109,Ledger!$F$5:$F$109,$A37,Ledger!$B$5:$B$109,"NIC Otjomuise Ext 10 (Erf 5221)") -> 0 | S37: =SUMIFS(Ledger!$C$5:$C$109,Ledger!$F$5:$F$109,$A37,Ledger!$B$5:$B$109,"Heavens Ark — Otjomuise") -> 0
A38: 44896 | B38: =SUMIFS(Ledger!$D$5:$D$109,Ledger!$F$5:$F$109,$A38) -> 0 | C38: =SUMIFS(Ledger!$E$5:$E$109,Ledger!$F$5:$F$109,$A38) -> 0 | D38: =B38+C38 -> 0 | E38: =D38 -> 0 | F38: =SUMIFS(Ledger!$C$5:$C$109,Ledger!$F$5:$F$109,$A38,Ledger!$B$5:$B$109,"Erf 1470 Khomasdal") -> 0 | G38: =SUMIFS(Ledger!$C$5:$C$109,Ledger!$F$5:$F$109,$A38,Ledger!$B$5:$B$109,"Dunescape Villas (Erf 5159)") -> 0 | H38: =SUMIFS(Ledger!$C$5:$C$109,Ledger!$F$5:$F$109,$A38,Ledger!$B$5:$B$109,"PAM Tree (Erf 5758)") -> 0 | I38: =SUMIFS(Ledger!$C$5:$C$109,Ledger!$F$5:$F$109,$A38,Ledger!$B$5:$B$109,"Turnstone Villas (Erf 8939)") -> 0 | J38: =SUMIFS(Ledger!$C$5:$C$109,Ledger!$F$5:$F$109,$A38,Ledger!$B$5:$B$109,"Lithon Nkurenkuru Ext 2") -> 0 | K38: =SUMIFS(Ledger!$C$5:$C$109,Ledger!$F$5:$F$109,$A38,Ledger!$B$5:$B$109,"Mondesa Palms") -> 0 | L38: =SUMIFS(Ledger!$C$5:$C$109,Ledger!$F$5:$F$109,$A38,Ledger!$B$5:$B$109,"The Ridge — Rocky Crest Ext 4") -> 0 | M38: =SUMIFS(Ledger!$C$5:$C$109,Ledger!$F$5:$F$109,$A38,Ledger!$B$5:$B$109,"Mango Cove (Otjomuise Ext 10)") -> 0 | N38: =SUMIFS(Ledger!$C$5:$C$109,Ledger!$F$5:$F$109,$A38,Ledger!$B$5:$B$109,"C-Breeze Heights") -> 0 | O38: =SUMIFS(Ledger!$C$5:$C$109,Ledger!$F$5:$F$109,$A38,Ledger!$B$5:$B$109,"Tama Estates") -> 0 | P38: =SUMIFS(Ledger!$C$5:$C$109,Ledger!$F$5:$F$109,$A38,Ledger!$B$5:$B$109,"Duma Tau — Kronlein") -> 0 | Q38: =SUMIFS(Ledger!$C$5:$C$109,Ledger!$F$5:$F$109,$A38,Ledger!$B$5:$B$109,"LIH Nkurenkuru Ph 1") -> 0 | R38: =SUMIFS(Ledger!$C$5:$C$109,Ledger!$F$5:$F$109,$A38,Ledger!$B$5:$B$109,"NIC Otjomuise Ext 10 (Erf 5221)") -> 0 | S38: =SUMIFS(Ledger!$C$5:$C$109,Ledger!$F$5:$F$109,$A38,Ledger!$B$5:$B$109,"Heavens Ark — Otjomuise") -> 0
A39: 44927 | B39: =SUMIFS(Ledger!$D$5:$D$109,Ledger!$F$5:$F$109,$A39) -> 0 | C39: =SUMIFS(Ledger!$E$5:$E$109,Ledger!$F$5:$F$109,$A39) -> 0 | D39: =B39+C39 -> 0 | E39: =D39 -> 0 | F39: =SUMIFS(Ledger!$C$5:$C$109,Ledger!$F$5:$F$109,$A39,Ledger!$B$5:$B$109,"Erf 1470 Khomasdal") -> 0 | G39: =SUMIFS(Ledger!$C$5:$C$109,Ledger!$F$5:$F$109,$A39,Ledger!$B$5:$B$109,"Dunescape Villas (Erf 5159)") -> 0 | H39: =SUMIFS(Ledger!$C$5:$C$109,Ledger!$F$5:$F$109,$A39,Ledger!$B$5:$B$109,"PAM Tree (Erf 5758)") -> 0 | I39: =SUMIFS(Ledger!$C$5:$C$109,Ledger!$F$5:$F$109,$A39,Ledger!$B$5:$B$109,"Turnstone Villas (Erf 8939)") -> 0 | J39: =SUMIFS(Ledger!$C$5:$C$109,Ledger!$F$5:$F$109,$A39,Ledger!$B$5:$B$109,"Lithon Nkurenkuru Ext 2") -> 0 | K39: =SUMIFS(Ledger!$C$5:$C$109,Ledger!$F$5:$F$109,$A39,Ledger!$B$5:$B$109,"Mondesa Palms") -> 0 | L39: =SUMIFS(Ledger!$C$5:$C$109,Ledger!$F$5:$F$109,$A39,Ledger!$B$5:$B$109,"The Ridge — Rocky Crest Ext 4") -> 0 | M39: =SUMIFS(Ledger!$C$5:$C$109,Ledger!$F$5:$F$109,$A39,Ledger!$B$5:$B$109,"Mango Cove (Otjomuise Ext 10)") -> 0 | N39: =SUMIFS(Ledger!$C$5:$C$109,Ledger!$F$5:$F$109,$A39,Ledger!$B$5:$B$109,"C-Breeze Heights") -> 0 | O39: =SUMIFS(Ledger!$C$5:$C$109,Ledger!$F$5:$F$109,$A39,Ledger!$B$5:$B$109,"Tama Estates") -> 0 | P39: =SUMIFS(Ledger!$C$5:$C$109,Ledger!$F$5:$F$109,$A39,Ledger!$B$5:$B$109,"Duma Tau — Kronlein") -> 0 | Q39: =SUMIFS(Ledger!$C$5:$C$109,Ledger!$F$5:$F$109,$A39,Ledger!$B$5:$B$109,"LIH Nkurenkuru Ph 1") -> 0 | R39: =SUMIFS(Ledger!$C$5:$C$109,Ledger!$F$5:$F$109,$A39,Ledger!$B$5:$B$109,"NIC Otjomuise Ext 10 (Erf 5221)") -> 0 | S39: =SUMIFS(Ledger!$C$5:$C$109,Ledger!$F$5:$F$109,$A39,Ledger!$B$5:$B$109,"Heavens Ark — Otjomuise") -> 0
A40: 44986 | B40: =SUMIFS(Ledger!$D$5:$D$109,Ledger!$F$5:$F$109,$A40) -> 0 | C40: =SUMIFS(Ledger!$E$5:$E$109,Ledger!$F$5:$F$109,$A40) -> 0 | D40: =B40+C40 -> 0 | E40: =D40 -> 0 | F40: =SUMIFS(Ledger!$C$5:$C$109,Ledger!$F$5:$F$109,$A40,Ledger!$B$5:$B$109,"Erf 1470 Khomasdal") -> 0 | G40: =SUMIFS(Ledger!$C$5:$C$109,Ledger!$F$5:$F$109,$A40,Ledger!$B$5:$B$109,"Dunescape Villas (Erf 5159)") -> 0 | H40: =SUMIFS(Ledger!$C$5:$C$109,Ledger!$F$5:$F$109,$A40,Ledger!$B$5:$B$109,"PAM Tree (Erf 5758)") -> 0 | I40: =SUMIFS(Ledger!$C$5:$C$109,Ledger!$F$5:$F$109,$A40,Ledger!$B$5:$B$109,"Turnstone Villas (Erf 8939)") -> 0 | J40: =SUMIFS(Ledger!$C$5:$C$109,Ledger!$F$5:$F$109,$A40,Ledger!$B$5:$B$109,"Lithon Nkurenkuru Ext 2") -> 0 | K40: =SUMIFS(Ledger!$C$5:$C$109,Ledger!$F$5:$F$109,$A40,Ledger!$B$5:$B$109,"Mondesa Palms") -> 0 | L40: =SUMIFS(Ledger!$C$5:$C$109,Ledger!$F$5:$F$109,$A40,Ledger!$B$5:$B$109,"The Ridge — Rocky Crest Ext 4") -> 0 | M40: =SUMIFS(Ledger!$C$5:$C$109,Ledger!$F$5:$F$109,$A40,Ledger!$B$5:$B$109,"Mango Cove (Otjomuise Ext 10)") -> 0 | N40: =SUMIFS(Ledger!$C$5:$C$109,Ledger!$F$5:$F$109,$A40,Ledger!$B$5:$B$109,"C-Breeze Heights") -> 0 | O40: =SUMIFS(Ledger!$C$5:$C$109,Ledger!$F$5:$F$109,$A40,Ledger!$B$5:$B$109,"Tama Estates") -> 0 | P40: =SUMIFS(Ledger!$C$5:$C$109,Ledger!$F$5:$F$109,$A40,Ledger!$B$5:$B$109,"Duma Tau — Kronlein") -> 0 | Q40: =SUMIFS(Ledger!$C$5:$C$109,Ledger!$F$5:$F$109,$A40,Ledger!$B$5:$B$109,"LIH Nkurenkuru Ph 1") -> 0 | R40: =SUMIFS(Ledger!$C$5:$C$109,Ledger!$F$5:$F$109,$A40,Ledger!$B$5:$B$109,"NIC Otjomuise Ext 10 (Erf 5221)") -> 0 | S40: =SUMIFS(Ledger!$C$5:$C$109,Ledger!$F$5:$F$109,$A40,Ledger!$B$5:$B$109,"Heavens Ark — Otjomuise") -> 0
A41: 45017 | B41: =SUMIFS(Ledger!$D$5:$D$109,Ledger!$F$5:$F$109,$A41) -> 0 | C41: =SUMIFS(Ledger!$E$5:$E$109,Ledger!$F$5:$F$109,$A41) -> 6983276.3 | D41: =B41+C41 -> 6983276.3 | E41: =D41 -> 6983276.3 | F41: =SUMIFS(Ledger!$C$5:$C$109,Ledger!$F$5:$F$109,$A41,Ledger!$B$5:$B$109,"Erf 1470 Khomasdal") -> 0 | G41: =SUMIFS(Ledger!$C$5:$C$109,Ledger!$F$5:$F$109,$A41,Ledger!$B$5:$B$109,"Dunescape Villas (Erf 5159)") -> 0 | H41: =SUMIFS(Ledger!$C$5:$C$109,Ledger!$F$5:$F$109,$A41,Ledger!$B$5:$B$109,"PAM Tree (Erf 5758)") -> 0 | I41: =SUMIFS(Ledger!$C$5:$C$109,Ledger!$F$5:$F$109,$A41,Ledger!$B$5:$B$109,"Turnstone Villas (Erf 8939)") -> 0 | J41: =SUMIFS(Ledger!$C$5:$C$109,Ledger!$F$5:$F$109,$A41,Ledger!$B$5:$B$109,"Lithon Nkurenkuru Ext 2") -> 0 | K41: =SUMIFS(Ledger!$C$5:$C$109,Ledger!$F$5:$F$109,$A41,Ledger!$B$5:$B$109,"Mondesa Palms") -> 0 | L41: =SUMIFS(Ledger!$C$5:$C$109,Ledger!$F$5:$F$109,$A41,Ledger!$B$5:$B$109,"The Ridge — Rocky Crest Ext 4") -> 0 | M41: =SUMIFS(Ledger!$C$5:$C$109,Ledger!$F$5:$F$109,$A41,Ledger!$B$5:$B$109,"Mango Cove (Otjomuise Ext 10)") -> 0 | N41: =SUMIFS(Ledger!$C$5:$C$109,Ledger!$F$5:$F$109,$A41,Ledger!$B$5:$B$109,"C-Breeze Heights") -> 0 | O41: =SUMIFS(Ledger!$C$5:$C$109,Ledger!$F$5:$F$109,$A41,Ledger!$B$5:$B$109,"Tama Estates") -> 0 | P41: =SUMIFS(Ledger!$C$5:$C$109,Ledger!$F$5:$F$109,$A41,Ledger!$B$5:$B$109,"Duma Tau — Kronlein") -> 694476.87 | Q41: =SUMIFS(Ledger!$C$5:$C$109,Ledger!$F$5:$F$109,$A41,Ledger!$B$5:$B$109,"LIH Nkurenkuru Ph 1") -> 0 | R41: =SUMIFS(Ledger!$C$5:$C$109,Ledger!$F$5:$F$109,$A41,Ledger!$B$5:$B$109,"NIC Otjomuise Ext 10 (Erf 5221)") -> 0 | S41: =SUMIFS(Ledger!$C$5:$C$109,Ledger!$F$5:$F$109,$A41,Ledger!$B$5:$B$109,"Heavens Ark — Otjomuise") -> 0
A42: 45047 | B42: =SUMIFS(Ledger!$D$5:$D$109,Ledger!$F$5:$F$109,$A42) -> 0 | C42: =SUMIFS(Ledger!$E$5:$E$109,Ledger!$F$5:$F$109,$A42) -> 0 | D42: =B42+C42 -> 0 | E42: =D42 -> 0 | F42: =SUMIFS(Ledger!$C$5:$C$109,Ledger!$F$5:$F$109,$A42,Ledger!$B$5:$B$109,"Erf 1470 Khomasdal") -> 0 | G42: =SUMIFS(Ledger!$C$5:$C$109,Ledger!$F$5:$F$109,$A42,Ledger!$B$5:$B$109,"Dunescape Villas (Erf 5159)") -> 0 | H42: =SUMIFS(Ledger!$C$5:$C$109,Ledger!$F$5:$F$109,$A42,Ledger!$B$5:$B$109,"PAM Tree (Erf 5758)") -> 0 | I42: =SUMIFS(Ledger!$C$5:$C$109,Ledger!$F$5:$F$109,$A42,Ledger!$B$5:$B$109,"Turnstone Villas (Erf 8939)") -> 0 | J42: =SUMIFS(Ledger!$C$5:$C$109,Ledger!$F$5:$F$109,$A42,Ledger!$B$5:$B$109,"Lithon Nkurenkuru Ext 2") -> 0 | K42: =SUMIFS(Ledger!$C$5:$C$109,Ledger!$F$5:$F$109,$A42,Ledger!$B$5:$B$109,"Mondesa Palms") -> 0 | L42: =SUMIFS(Ledger!$C$5:$C$109,Ledger!$F$5:$F$109,$A42,Ledger!$B$5:$B$109,"The Ridge — Rocky Crest Ext 4") -> 0 | M42: =SUMIFS(Ledger!$C$5:$C$109,Ledger!$F$5:$F$109,$A42,Ledger!$B$5:$B$109,"Mango Cove (Otjomuise Ext 10)") -> 0 | N42: =SUMIFS(Ledger!$C$5:$C$109,Ledger!$F$5:$F$109,$A42,Ledger!$B$5:$B$109,"C-Breeze Heights") -> 0 | O42: =SUMIFS(Ledger!$C$5:$C$109,Ledger!$F$5:$F$109,$A42,Ledger!$B$5:$B$109,"Tama Estates") -> 0 | P42: =SUMIFS(Ledger!$C$5:$C$109,Ledger!$F$5:$F$109,$A42,Ledger!$B$5:$B$109,"Duma Tau — Kronlein") -> 0 | Q42: =SUMIFS(Ledger!$C$5:$C$109,Ledger!$F$5:$F$109,$A42,Ledger!$B$5:$B$109,"LIH Nkurenkuru Ph 1") -> 0 | R42: =SUMIFS(Ledger!$C$5:$C$109,Ledger!$F$5:$F$109,$A42,Ledger!$B$5:$B$109,"NIC Otjomuise Ext 10 (Erf 5221)") -> 0 | S42: =SUMIFS(Ledger!$C$5:$C$109,Ledger!$F$5:$F$109,$A42,Ledger!$B$5:$B$109,"Heavens Ark — Otjomuise") -> 0
A43: 45078 | B43: =SUMIFS(Ledger!$D$5:$D$109,Ledger!$F$5:$F$109,$A43) -> 0 | C43: =SUMIFS(Ledger!$E$5:$E$109,Ledger!$F$5:$F$109,$A43) -> 1515807.3 | D43: =B43+C43 -> 1515807.3 | E43: =D43 -> 1515807.3 | F43: =SUMIFS(Ledger!$C$5:$C$109,Ledger!$F$5:$F$109,$A43,Ledger!$B$5:$B$109,"Erf 1470 Khomasdal") -> 0 | G43: =SUMIFS(Ledger!$C$5:$C$109,Ledger!$F$5:$F$109,$A43,Ledger!$B$5:$B$109,"Dunescape Villas (Erf 5159)") -> 0 | H43: =SUMIFS(Ledger!$C$5:$C$109,Ledger!$F$5:$F$109,$A43,Ledger!$B$5:$B$109,"PAM Tree (Erf 5758)") -> 0 | I43: =SUMIFS(Ledger!$C$5:$C$109,Ledger!$F$5:$F$109,$A43,Ledger!$B$5:$B$109,"Turnstone Villas (Erf 8939)") -> 0 | J43: =SUMIFS(Ledger!$C$5:$C$109,Ledger!$F$5:$F$109,$A43,Ledger!$B$5:$B$109,"Lithon Nkurenkuru Ext 2") -> 0 | K43: =SUMIFS(Ledger!$C$5:$C$109,Ledger!$F$5:$F$109,$A43,Ledger!$B$5:$B$109,"Mondesa Palms") -> 0 | L43: =SUMIFS(Ledger!$C$5:$C$109,Ledger!$F$5:$F$109,$A43,Ledger!$B$5:$B$109,"The Ridge — Rocky Crest Ext 4") -> 0 | M43: =SUMIFS(Ledger!$C$5:$C$109,Ledger!$F$5:$F$109,$A43,Ledger!$B$5:$B$109,"Mango Cove (Otjomuise Ext 10)") -> 0 | N43: =SUMIFS(Ledger!$C$5:$C$109,Ledger!$F$5:$F$109,$A43,Ledger!$B$5:$B$109,"C-Breeze Heights") -> 0 | O43: =SUMIFS(Ledger!$C$5:$C$109,Ledger!$F$5:$F$109,$A43,Ledger!$B$5:$B$109,"Tama Estates") -> 0 | P43: =SUMIFS(Ledger!$C$5:$C$109,Ledger!$F$5:$F$109,$A43,Ledger!$B$5:$B$109,"Duma Tau — Kronlein") -> 451182.19 | Q43: =SUMIFS(Ledger!$C$5:$C$109,Ledger!$F$5:$F$109,$A43,Ledger!$B$5:$B$109,"LIH Nkurenkuru Ph 1") -> 0 | R43: =SUMIFS(Ledger!$C$5:$C$109,Ledger!$F$5:$F$109,$A43,Ledger!$B$5:$B$109,"NIC Otjomuise Ext 10 (Erf 5221)") -> 0 | S43: =SUMIFS(Ledger!$C$5:$C$109,Ledger!$F$5:$F$109,$A43,Ledger!$B$5:$B$109,"Heavens Ark — Otjomuise") -> 0
A44: 45108 | B44: =SUMIFS(Ledger!$D$5:$D$109,Ledger!$F$5:$F$109,$A44) -> 0 | C44: =SUMIFS(Ledger!$E$5:$E$109,Ledger!$F$5:$F$109,$A44) -> 0 | D44: =B44+C44 -> 0 | E44: =D44 -> 0 | F44: =SUMIFS(Ledger!$C$5:$C$109,Ledger!$F$5:$F$109,$A44,Ledger!$B$5:$B$109,"Erf 1470 Khomasdal") -> 0 | G44: =SUMIFS(Ledger!$C$5:$C$109,Ledger!$F$5:$F$109,$A44,Ledger!$B$5:$B$109,"Dunescape Villas (Erf 5159)") -> 0 | H44: =SUMIFS(Ledger!$C$5:$C$109,Ledger!$F$5:$F$109,$A44,Ledger!$B$5:$B$109,"PAM Tree (Erf 5758)") -> 0 | I44: =SUMIFS(Ledger!$C$5:$C$109,Ledger!$F$5:$F$109,$A44,Ledger!$B$5:$B$109,"Turnstone Villas (Erf 8939)") -> 0 | J44: =SUMIFS(Ledger!$C$5:$C$109,Ledger!$F$5:$F$109,$A44,Ledger!$B$5:$B$109,"Lithon Nkurenkuru Ext 2") -> 0 | K44: =SUMIFS(Ledger!$C$5:$C$109,Ledger!$F$5:$F$109,$A44,Ledger!$B$5:$B$109,"Mondesa Palms") -> 0 | L44: =SUMIFS(Ledger!$C$5:$C$109,Ledger!$F$5:$F$109,$A44,Ledger!$B$5:$B$109,"The Ridge — Rocky Crest Ext 4") -> 0 | M44: =SUMIFS(Ledger!$C$5:$C$109,Ledger!$F$5:$F$109,$A44,Ledger!$B$5:$B$109,"Mango Cove (Otjomuise Ext 10)") -> 0 | N44: =SUMIFS(Ledger!$C$5:$C$109,Ledger!$F$5:$F$109,$A44,Ledger!$B$5:$B$109,"C-Breeze Heights") -> 0 | O44: =SUMIFS(Ledger!$C$5:$C$109,Ledger!$F$5:$F$109,$A44,Ledger!$B$5:$B$109,"Tama Estates") -> 0 | P44: =SUMIFS(Ledger!$C$5:$C$109,Ledger!$F$5:$F$109,$A44,Ledger!$B$5:$B$109,"Duma Tau — Kronlein") -> 0 | Q44: =SUMIFS(Ledger!$C$5:$C$109,Ledger!$F$5:$F$109,$A44,Ledger!$B$5:$B$109,"LIH Nkurenkuru Ph 1") -> 0 | R44: =SUMIFS(Ledger!$C$5:$C$109,Ledger!$F$5:$F$109,$A44,Ledger!$B$5:$B$109,"NIC Otjomuise Ext 10 (Erf 5221)") -> 0 | S44: =SUMIFS(Ledger!$C$5:$C$109,Ledger!$F$5:$F$109,$A44,Ledger!$B$5:$B$109,"Heavens Ark — Otjomuise") -> 0
A45: 45139 | B45: =SUMIFS(Ledger!$D$5:$D$109,Ledger!$F$5:$F$109,$A45) -> -6000000 | C45: =SUMIFS(Ledger!$E$5:$E$109,Ledger!$F$5:$F$109,$A45) -> 0 | D45: =B45+C45 -> -6000000 | E45: =D45 -> -6000000 | F45: =SUMIFS(Ledger!$C$5:$C$109,Ledger!$F$5:$F$109,$A45,Ledger!$B$5:$B$109,"Erf 1470 Khomasdal") -> 0 | G45: =SUMIFS(Ledger!$C$5:$C$109,Ledger!$F$5:$F$109,$A45,Ledger!$B$5:$B$109,"Dunescape Villas (Erf 5159)") -> 0 | H45: =SUMIFS(Ledger!$C$5:$C$109,Ledger!$F$5:$F$109,$A45,Ledger!$B$5:$B$109,"PAM Tree (Erf 5758)") -> 0 | I45: =SUMIFS(Ledger!$C$5:$C$109,Ledger!$F$5:$F$109,$A45,Ledger!$B$5:$B$109,"Turnstone Villas (Erf 8939)") -> 0 | J45: =SUMIFS(Ledger!$C$5:$C$109,Ledger!$F$5:$F$109,$A45,Ledger!$B$5:$B$109,"Lithon Nkurenkuru Ext 2") -> 0 | K45: =SUMIFS(Ledger!$C$5:$C$109,Ledger!$F$5:$F$109,$A45,Ledger!$B$5:$B$109,"Mondesa Palms") -> 0 | L45: =SUMIFS(Ledger!$C$5:$C$109,Ledger!$F$5:$F$109,$A45,Ledger!$B$5:$B$109,"The Ridge — Rocky Crest Ext 4") -> 0 | M45: =SUMIFS(Ledger!$C$5:$C$109,Ledger!$F$5:$F$109,$A45,Ledger!$B$5:$B$109,"Mango Cove (Otjomuise Ext 10)") -> 0 | N45: =SUMIFS(Ledger!$C$5:$C$109,Ledger!$F$5:$F$109,$A45,Ledger!$B$5:$B$109,"C-Breeze Heights") -> 0 | O45: =SUMIFS(Ledger!$C$5:$C$109,Ledger!$F$5:$F$109,$A45,Ledger!$B$5:$B$109,"Tama Estates") -> 0 | P45: =SUMIFS(Ledger!$C$5:$C$109,Ledger!$F$5:$F$109,$A45,Ledger!$B$5:$B$109,"Duma Tau — Kronlein") -> 0 | Q45: =SUMIFS(Ledger!$C$5:$C$109,Ledger!$F$5:$F$109,$A45,Ledger!$B$5:$B$109,"LIH Nkurenkuru Ph 1") -> 0 | R45: =SUMIFS(Ledger!$C$5:$C$109,Ledger!$F$5:$F$109,$A45,Ledger!$B$5:$B$109,"NIC Otjomuise Ext 10 (Erf 5221)") -> 0 | S45: =SUMIFS(Ledger!$C$5:$C$109,Ledger!$F$5:$F$109,$A45,Ledger!$B$5:$B$109,"Heavens Ark — Otjomuise") -> 0
A46: 45170 | B46: =SUMIFS(Ledger!$D$5:$D$109,Ledger!$F$5:$F$109,$A46) -> 0 | C46: =SUMIFS(Ledger!$E$5:$E$109,Ledger!$F$5:$F$109,$A46) -> 0 | D46: =B46+C46 -> 0 | E46: =D46 -> 0 | F46: =SUMIFS(Ledger!$C$5:$C$109,Ledger!$F$5:$F$109,$A46,Ledger!$B$5:$B$109,"Erf 1470 Khomasdal") -> 0 | G46: =SUMIFS(Ledger!$C$5:$C$109,Ledger!$F$5:$F$109,$A46,Ledger!$B$5:$B$109,"Dunescape Villas (Erf 5159)") -> 0 | H46: =SUMIFS(Ledger!$C$5:$C$109,Ledger!$F$5:$F$109,$A46,Ledger!$B$5:$B$109,"PAM Tree (Erf 5758)") -> 0 | I46: =SUMIFS(Ledger!$C$5:$C$109,Ledger!$F$5:$F$109,$A46,Ledger!$B$5:$B$109,"Turnstone Villas (Erf 8939)") -> 0 | J46: =SUMIFS(Ledger!$C$5:$C$109,Ledger!$F$5:$F$109,$A46,Ledger!$B$5:$B$109,"Lithon Nkurenkuru Ext 2") -> 0 | K46: =SUMIFS(Ledger!$C$5:$C$109,Ledger!$F$5:$F$109,$A46,Ledger!$B$5:$B$109,"Mondesa Palms") -> 0 | L46: =SUMIFS(Ledger!$C$5:$C$109,Ledger!$F$5:$F$109,$A46,Ledger!$B$5:$B$109,"The Ridge — Rocky Crest Ext 4") -> 0 | M46: =SUMIFS(Ledger!$C$5:$C$109,Ledger!$F$5:$F$109,$A46,Ledger!$B$5:$B$109,"Mango Cove (Otjomuise Ext 10)") -> 0 | N46: =SUMIFS(Ledger!$C$5:$C$109,Ledger!$F$5:$F$109,$A46,Ledger!$B$5:$B$109,"C-Breeze Heights") -> 0 | O46: =SUMIFS(Ledger!$C$5:$C$109,Ledger!$F$5:$F$109,$A46,Ledger!$B$5:$B$109,"Tama Estates") -> 0 | P46: =SUMIFS(Ledger!$C$5:$C$109,Ledger!$F$5:$F$109,$A46,Ledger!$B$5:$B$109,"Duma Tau — Kronlein") -> 0 | Q46: =SUMIFS(Ledger!$C$5:$C$109,Ledger!$F$5:$F$109,$A46,Ledger!$B$5:$B$109,"LIH Nkurenkuru Ph 1") -> 0 | R46: =SUMIFS(Ledger!$C$5:$C$109,Ledger!$F$5:$F$109,$A46,Ledger!$B$5:$B$109,"NIC Otjomuise Ext 10 (Erf 5221)") -> 0 | S46: =SUMIFS(Ledger!$C$5:$C$109,Ledger!$F$5:$F$109,$A46,Ledger!$B$5:$B$109,"Heavens Ark — Otjomuise") -> 0
A47: 45200 | B47: =SUMIFS(Ledger!$D$5:$D$109,Ledger!$F$5:$F$109,$A47) -> -2500000 | C47: =SUMIFS(Ledger!$E$5:$E$109,Ledger!$F$5:$F$109,$A47) -> 0 | D47: =B47+C47 -> -2500000 | E47: =D47 -> -2500000 | F47: =SUMIFS(Ledger!$C$5:$C$109,Ledger!$F$5:$F$109,$A47,Ledger!$B$5:$B$109,"Erf 1470 Khomasdal") -> 0 | G47: =SUMIFS(Ledger!$C$5:$C$109,Ledger!$F$5:$F$109,$A47,Ledger!$B$5:$B$109,"Dunescape Villas (Erf 5159)") -> 0 | H47: =SUMIFS(Ledger!$C$5:$C$109,Ledger!$F$5:$F$109,$A47,Ledger!$B$5:$B$109,"PAM Tree (Erf 5758)") -> 0 | I47: =SUMIFS(Ledger!$C$5:$C$109,Ledger!$F$5:$F$109,$A47,Ledger!$B$5:$B$109,"Turnstone Villas (Erf 8939)") -> 0 | J47: =SUMIFS(Ledger!$C$5:$C$109,Ledger!$F$5:$F$109,$A47,Ledger!$B$5:$B$109,"Lithon Nkurenkuru Ext 2") -> 0 | K47: =SUMIFS(Ledger!$C$5:$C$109,Ledger!$F$5:$F$109,$A47,Ledger!$B$5:$B$109,"Mondesa Palms") -> 0 | L47: =SUMIFS(Ledger!$C$5:$C$109,Ledger!$F$5:$F$109,$A47,Ledger!$B$5:$B$109,"The Ridge — Rocky Crest Ext 4") -> 0 | M47: =SUMIFS(Ledger!$C$5:$C$109,Ledger!$F$5:$F$109,$A47,Ledger!$B$5:$B$109,"Mango Cove (Otjomuise Ext 10)") -> 0 | N47: =SUMIFS(Ledger!$C$5:$C$109,Ledger!$F$5:$F$109,$A47,Ledger!$B$5:$B$109,"C-Breeze Heights") -> 0 | O47: =SUMIFS(Ledger!$C$5:$C$109,Ledger!$F$5:$F$109,$A47,Ledger!$B$5:$B$109,"Tama Estates") -> 0 | P47: =SUMIFS(Ledger!$C$5:$C$109,Ledger!$F$5:$F$109,$A47,Ledger!$B$5:$B$109,"Duma Tau — Kronlein") -> 0 | Q47: =SUMIFS(Ledger!$C$5:$C$109,Ledger!$F$5:$F$109,$A47,Ledger!$B$5:$B$109,"LIH Nkurenkuru Ph 1") -> 0 | R47: =SUMIFS(Ledger!$C$5:$C$109,Ledger!$F$5:$F$109,$A47,Ledger!$B$5:$B$109,"NIC Otjomuise Ext 10 (Erf 5221)") -> 0 | S47: =SUMIFS(Ledger!$C$5:$C$109,Ledger!$F$5:$F$109,$A47,Ledger!$B$5:$B$109,"Heavens Ark — Otjomuise") -> 0
... A69: 46235 | B69: =SUMIFS(Ledger!$D$5:$D$109,Ledger!$F$5:$F$109,$A69) -> -7000000 | C69: =SUMIFS(Ledger!$E$5:$E$109,Ledger!$F$5:$F$109,$A69) -> 0 | D69: =B69+C69 -> -7000000 | E69: =D69 -> -7000000 | F69: =SUMIFS(Ledger!$C$5:$C$109,Ledger!$F$5:$F$109,$A69,Ledger!$B$5:$B$109,"Erf 1470 Khomasdal") -> 0 | G69: =SUMIFS(Ledger!$C$5:$C$109,Ledger!$F$5:$F$109,$A69,Ledger!$B$5:$B$109,"Dunescape Villas (Erf 5159)") -> 0 | H69: =SUMIFS(Ledger!$C$5:$C$109,Ledger!$F$5:$F$109,$A69,Ledger!$B$5:$B$109,"PAM Tree (Erf 5758)") -> 0 | I69: =SUMIFS(Ledger!$C$5:$C$109,Ledger!$F$5:$F$109,$A69,Ledger!$B$5:$B$109,"Turnstone Villas (Erf 8939)") -> 0 | J69: =SUMIFS(Ledger!$C$5:$C$109,Ledger!$F$5:$F$109,$A69,Ledger!$B$5:$B$109,"Lithon Nkurenkuru Ext 2") -> 0 | K69: =SUMIFS(Ledger!$C$5:$C$109,Ledger!$F$5:$F$109,$A69,Ledger!$B$5:$B$109,"Mondesa Palms") -> 0 | L69: =SUMIFS(Ledger!$C$5:$C$109,Ledger!$F$5:$F$109,$A69,Ledger!$B$5:$B$109,"The Ridge — Rocky Crest Ext 4") -> 0 | M69: =SUMIFS(Ledger!$C$5:$C$109,Ledger!$F$5:$F$109,$A69,Ledger!$B$5:$B$109,"Mango Cove (Otjomuise Ext 10)") -> 0 | N69: =SUMIFS(Ledger!$C$5:$C$109,Ledger!$F$5:$F$109,$A69,Ledger!$B$5:$B$109,"C-Breeze Heights") -> 0 | O69: =SUMIFS(Ledger!$C$5:$C$109,Ledger!$F$5:$F$109,$A69,Ledger!$B$5:$B$109,"Tama Estates") -> 0 | P69: =SUMIFS(Ledger!$C$5:$C$109,Ledger!$F$5:$F$109,$A69,Ledger!$B$5:$B$109,"Duma Tau — Kronlein") -> 0 | Q69: =SUMIFS(Ledger!$C$5:$C$109,Ledger!$F$5:$F$109,$A69,Ledger!$B$5:$B$109,"LIH Nkurenkuru Ph 1") -> 0 | R69: =SUMIFS(Ledger!$C$5:$C$109,Ledger!$F$5:$F$109,$A69,Ledger!$B$5:$B$109,"NIC Otjomuise Ext 10 (Erf 5221)") -> 0 | S69: =SUMIFS(Ledger!$C$5:$C$109,Ledger!$F$5:$F$109,$A69,Ledger!$B$5:$B$109,"Heavens Ark — Otjomuise") -> 0
A70: TOTAL | B70: =SUM(B5:B69) -> -3.7100423e+08 | C70: =SUM(C5:C69) -> 2.078e+08 | D70: =SUM(D5:D69) -> -1.6320423e+08 | E70: =E69 -> -7000000 | F70: =SUM(F5:F69) -> 0 | G70: =SUM(G5:G69) -> 0 | H70: =SUM(H5:H69) -> 0 | I70: =SUM(I5:I69) -> 0 | J70: =SUM(J5:J69) -> 0 | K70: =SUM(K5:K69) -> 0 | L70: =SUM(L5:L69) -> 0 | M70: =SUM(M5:M69) -> 0 | ... S70: =SUM(S5:S69) -> 0
A72: Control: row totals tie to Ledger row 163 and to Sheet 2 column C/D.

Sheet Ledger
A1: CONSOLIDATED EVENT LEDGER — every dated fund cash flow behind Sheets 1-4
A2: Fund perspective: capital deployed shown negative, distributions received positive. All amounts N$ (NAD). Blue = source figure typed from a model; nothing on this tab is derived.
A4: Date | B4: Project | C4: Amount (N$) | D4: Drawdown (N$) | E4: Distribution (N$) | F4: Month key | G4: Source workbook / tab
A5: 43067 | B5: Aromatic Fresh Notes Investments Pty Ltd - Erf 1470 Khomasdal | C5: -45500000 | D5: =IF(C5<0,C5,0) -> -45500000 | E5: =IF(C5>0,C5,0) -> 0 | F5: =DATE(YEAR(A5),MONTH(A5),1) -> 43040 | G5: Drawdown Register
A6: 43067 | B6: LIH- Nkurenkuru Ph 1 | C6: -2200000 | D6: =IF(C6<0,C6,0) -> -2200000 | E6: =IF(C6>0,C6,0) -> 0 | F6: =DATE(YEAR(A6),MONTH(A6),1) -> 43040 | G6: Drawdown Register
A7: 43168 | B7: Duma Tau — Kronlein | C7: -22000000 | D7: =IF(C7<0,C7,0) -> -22000000 | E7: =IF(C7>0,C7,0) -> 0 | F7: =DATE(YEAR(A7),MONTH(A7),1) -> 43160 | G7: Drawdown Register
A8: 43216 | B8: MPG _ Heaven's Ark — Otjomuise Lifestyle Estate | C8: -10000000 | D8: =IF(C8<0,C8,0) -> -10000000 | E8: =IF(C8>0,C8,0) -> 0 | F8: =DATE(YEAR(A8),MONTH(A8),1) -> 43191 | G8: Drawdown Register
A9: 43280 | B9: LIH- Nkurenkuru Ph 1 | C9: -700000 | D9: =IF(C9<0,C9,0) -> -700000 | E9: =IF(C9>0,C9,0) -> 0 | F9: =DATE(YEAR(A9),MONTH(A9),1) -> 43252 | G9: Drawdown Register
A10: 43304 | B10: LIH- Nkurenkuru Ph 1 | C10: -4300000 | D10: =IF(C10<0,C10,0) -> -4300000 | E10: =IF(C10>0,C10,0) -> 0 | F10: =DATE(YEAR(A10),MONTH(A10),1) -> 43282 | G10: Drawdown Register
A11: 43322 | B11: Duma Tau — Kronlein | C11: -6000000 | D11: =IF(C11<0,C11,0) -> -6000000 | E11: =IF(C11>0,C11,0) -> 0 | F11: =DATE(YEAR(A11),MONTH(A11),1) -> 43313 | G11: Drawdown Register
A12: 43322 | B12: LIH- Nkurenkuru Ph 1 | C12: -5000000 | D12: =IF(C12<0,C12,0) -> -5000000 | E12: =IF(C12>0,C12,0) -> 0 | F12: =DATE(YEAR(A12),MONTH(A12),1) -> 43313 | G12: Drawdown Register
A13: 43356 | B13: Duma Tau — Kronlein | C13: 1302000 | D13: =IF(C13<0,C13,0) -> 0 | E13: =IF(C13>0,C13,0) -> 1302000 | F13: =DATE(YEAR(A13),MONTH(A13),1) -> 43344 | G13: Drawdown Register
A14: 43362 | B14: Aromatic Fresh Notes Investments Pty Ltd - Erf 1470 Khomasdal | C14: -1500000 | D14: =IF(C14<0,C14,0) -> -1500000 | E14: =IF(C14>0,C14,0) -> 0 | F14: =DATE(YEAR(A14),MONTH(A14),1) -> 43344 | G14: Drawdown Register
A15: 43362 | B15: MPG _ Heaven's Ark — Otjomuise Lifestyle Estate | C15: -1000000 | D15: =IF(C15<0,C15,0) -> -1000000 | E15: =IF(C15>0,C15,0) -> 0 | F15: =DATE(YEAR(A15),MONTH(A15),1) -> 43344 | G15: Drawdown Register
A16: 43384 | B16: MPG _ Heaven's Ark — Otjomuise Lifestyle Estate | C16: -10000000 | D16: =IF(C16<0,C16,0) -> -10000000 | E16: =IF(C16>0,C16,0) -> 0 | F16: =DATE(YEAR(A16),MONTH(A16),1) -> 43374 | G16: Drawdown Register
... A108: 46252 | B108: Blue Mont Pty Ltd The Ridge | C108: -7000000 | D108: =IF(C108<0,C108,0) -> -7000000 | E108: =IF(C108>0,C108,0) -> 0 | F108: =DATE(YEAR(A108),MONTH(A108),1) -> 46235 | G108: Drawdown Register
D109: =SUBTOTAL(109,Table1[Drawdown (N$)]) -> -3.7100423e+08 | E109: =SUBTOTAL(109,Table1[Distribution (N$)]) -> 2.078e+08
B110: TOTAL | C110: =SUM(C5:C109) -> -1.6320423e+08 | D110: =SUM(D5:D109) -> -7.4200846e+08 | E110: =SUM(E5:E109) -> 4.156e+08
A112: PROJECT SUMMARY — TOTAL DRAWDOWNS & DISTRIBUTIONS
A113: Project | B113: Total Drawdown (N$) | C113: Total Distribution (N$)
A114: Erf 1470 Khomasdal | B114: =SUMIF($B$5:$B$109,A114,$D$5:$D$109) -> 0 | C114: =SUMIF($B$5:$B$109,A114,$E$5:$E$109) -> 0
A115: Dunescape Villas (Erf 5159) | B115: =SUMIF($B$5:$B$109,A115,$D$5:$D$109) -> 0 | C115: =SUMIF($B$5:$B$109,A115,$E$5:$E$109) -> 0
A116: PAM Tree (Erf 5758) | B116: =SUMIF($B$5:$B$109,A116,$D$5:$D$109) -> 0 | C116: =SUMIF($B$5:$B$109,A116,$E$5:$E$109) -> 0
A117: Turnstone Villas (Erf 8939) | B117: =SUMIF($B$5:$B$109,A117,$D$5:$D$109) -> 0 | C117: =SUMIF($B$5:$B$109,A117,$E$5:$E$109) -> 0
A118: Lithon Nkurenkuru Ext 2 | B118: =SUMIF($B$5:$B$109,A118,$D$5:$D$109) -> 0 | C118: =SUMIF($B$5:$B$109,A118,$E$5:$E$109) -> 0
A119: Mondesa Palms | B119: =SUMIF($B$5:$B$109,A119,$D$5:$D$109) -> 0 | C119: =SUMIF($B$5:$B$109,A119,$E$5:$E$109) -> 0
A120: The Ridge — Rocky Crest Ext 4 | B120: =SUMIF($B$5:$B$109,A120,$D$5:$D$109) -> 0 | C120: =SUMIF($B$5:$B$109,A120,$E$5:$E$109) -> 0
A121: Mango Cove (Otjomuise Ext 10) | B121: =SUMIF($B$5:$B$109,A121,$D$5:$D$109) -> 0 | C121: =SUMIF($B$5:$B$109,A121,$E$5:$E$109) -> 0
A122: C-Breeze Heights | B122: =SUMIF($B$5:$B$109,A122,$D$5:$D$109) -> 0 | C122: =SUMIF($B$5:$B$109,A122,$E$5:$E$109) -> 0
A123: Tama Estates | B123: =SUMIF($B$5:$B$109,A123,$D$5:$D$109) -> 0 | C123: =SUMIF($B$5:$B$109,A123,$E$5:$E$109) -> 0
A124: Duma Tau — Kronlein | B124: =SUMIF($B$5:$B$109,A124,$D$5:$D$109) -> -36109399 | C124: =SUMIF($B$5:$B$109,A124,$E$5:$E$109) -> 42507268
A125: LIH Nkurenkuru Ph 1 | B125: =SUMIF($B$5:$B$109,A125,$D$5:$D$109) -> 0 | C125: =SUMIF($B$5:$B$109,A125,$E$5:$E$109) -> 0
... A127: Heavens Ark — Otjomuise | B127: =SUMIF($B$5:$B$109,A127,$D$5:$D$109) -> 0 | C127: =SUMIF($B$5:$B$109,A127,$E$5:$E$109) -> 0
A128: TOTAL | B128: =SUM(B114:B127) -> -36109399 | C128: =SUM(C114:C127) -> 42507268
E129: =B128-B122-B123 -> -36109399

Sheet Notes & Reconciliations
A1: SOURCES, ASSUMPTIONS AND OPEN RECONCILIATIONS
A2: Read this before the numbers go into a GIPF pack. Items marked OPEN are unresolved differences between two documents in the folder; neither has been overridden.
A4: # | B4: Item | C4: Status | D4: Detail
A5: 1 | B5: Treatment of Tama Estates and C-Breeze Heights | C5: APPLIED | D5: Per instruction, the 'Equity - Investor' line in the Tama Estates Vert Development Model (N$10,100,000 committed, 20.8% IRR, 1.32x EMx, distributions N$13,341,540) and the 'Equity - Mezzanine' line in the C-Breeze Heights Vert Development Model (N$1,994,992, 18.0% IRR, 1.15x EMx, distributions N$2,428,302) are treated as the fund's own returns. Note the labels in the models are 'Equity - Investor' and 'Equity - Mezzanine' respectively, not both as given.
A6: 2 | B6: C-Breeze equity line vs the KAHF facility | C6: OPEN | D6: The Vert model carries Equity-Mezzanine of N$1,994,992. The signed KAHF facility is N$5,000,000 and N$4,389,111 has actually been drawn (29-May, 04-Jun and 26-Jun 2026). The Vert model is dated 05-03-2026 and pre-dates the drawdowns. Sheet 2 uses the drawn capital for cash and the Vert model's 18.0% for IRR, per instruction. The model should be re-run on the N$5m facility.
A7: 3 | B7: Fund drawdown register total rows are stale | C7: OPEN | D7: In the fund drawdown register (Drawdowns tab), row 113 'Total Drawdowns' sums only columns B, C, D, E, F, G, I and O — it omits Dunescape, Turnstone, PAM Tree, Mondesa, Rocky Crest and Mango Cove entirely. Row 114 'Total Distributions' likewise omits the N$24.0m Dunescape repayment. The stated totals of N$243,535,135 and N$183,800,002 are therefore both understated. This workbook re-sums the register line by line: N$368,755,917 deployed and N$267,283,868 received.
A8: 4 | B8: Erf 1470 Khomasdal — capital advanced | C8: OPEN | D8: The fund register carries N$96,688,000 of drawdowns; the project workbook's own notice register carries N$95,611,595. The difference is exactly N$1,076,405.04, a 27-Jun-2019 entry present in the register and absent from the project ledger.
A9: 5 | B9: Duma Tau — register vs project ledger | C9: OPEN | D9: Register: N$36,109,399 out / N$42,507,268 in. Project workbook: N$38,910,481 out / N$42,162,690 in. The workbook itself flags both differences (facility over-advanced by N$10,910,481; register basis differs by N$827,119). Sheet 4 follows the register because it is the only dated source; Sheet 2's IRR follows the project workbook.
A10: 6 | B10: Heavens Ark — register nets recycled capital | C10: OPEN | D10: Register: N$65,000,000 out / N$75,599,843 in. Project workbook: N$80,000,936 out / N$90,600,779 in. The N$15,000,936 difference is the Aug-2019 recycle, netted in the register and shown gross in the workbook. Net profit is N$10,599,843 on both bases.
A11: 7 | B11: Mango Cove — two irreconcilable positions | C11: OPEN | D11: The fund register and the KAHF Projects schedule both show N$12,000,000 advanced on 29-Sep-2025 against a N$20,000,000 approval. The interest schedule ('C - Otjimuise Ext 10, Margo Cov') shows a separate N$15,000,000 facility granted 01-May-2026 at 14% NACM with only N$5,028,879 drawn and a balance of N$5,108,318 at 31-Jul-2026. This workbook uses N$12,000,000. Resolve before the pack goes out.
A12: 8 | B12: Mondesa Palms — the model is provisional | C12: OPEN | D12: The Mondesa model's own dashboard states that no facility agreement, drawdown notice or investment approval was supplied, and that facility size, interest rate, first drawdown date, drawn-to-date and unit selling price are all placeholders. Its 18.94% IRR is therefore provisional. The register shows N$15,000,000 drawn (Aug-25 and Jun-26); the KAHF Projects schedule shows N$12,958,884; the model assumes N$11,365,558.
A13: 9 | B13: Mondesa Palms — scope | C13: OPEN | D13: The hardcoded plan is 134 units across 3 erven (4420 / 4421 / 4422). The only model in the folder covers Erf 4420 and 40 units. The KAHF Projects schedule shows 131. No model exists for the other two erven.
A14: 10 | B14: The Ridge — Rocky Crest unit count | C14: OPEN | D14: Hardcoded plan is 38 units. The KAHF Projects schedule shows 40 at 30-Sep-2027 and 108 extended. The financial model does not state a unit count at all.
A15: 11 | B15: PAM Tree — return dashboard is broken | C15: OPEN | D15: Two PAM Tree workbooks exist. 'PAM Tree/KAHF_PAM Tree Performance.xlsx' contains Turnstone Villas data, not PAM Tree data — its ledger shows the N$16.3m / N$18.97m Turnstone figures. 'Lithon Nkurenkuru Ext 2/KAHF_PAM Tree Performance(CHQ).xlsx' has the correct N$45m ledger but its dashboard returns a REF error and its total row mis-sums to a -33.5% IRR. Sheet 2 uses the 24% reported on Contract Parameters D31.
A16: 12 | B16: Turnstone Villas — negative realised IRR | C16: NOTED | D16: The -10.6% on Sheet 2 is the workbook's own realised XIRR, which deliberately excludes the N$21.3m residual value. On a total-value basis the project returns 2.16x. Present both, or the number reads as a loss.
... A26: 22 | B26: Valuation dates are not uniform | C26: NOTED | D26: Carrying values on Sheet 2 are as at: Khomasdal 28-02-26, Dunescape 28-02-26, Lithon 31-07-26, Turnstone 31-07-26, Duma Tau and LIH at close-out, and cost for Mondesa, Rocky Crest and Mango Cove. A single valuation date would need fresh valuations.

Sheet 5. Cash IRR & Residual
A1: SHEET 5 — FUND-LEVEL CASH IRR & RESIDUAL, AS AT 30 SEPTEMBER 2026
A2: Methodology: XIRR over every dated fund-level cash flow on the Ledger tab (capital deployed negative, distributions received positive), plus one terminal cash flow dated 30-Sep-2026 equal to the portfolio's carrying value (NAV) — the same 'XIRR incl. NAV' approach used per-project on Sheet 2, column L. Rebuilt to match the Ledger 1:1 after restructuring; rows below link live to Ledger!A5:C112.
A4: A. DATED FUND CASH FLOWS (LINKED TO LEDGER)
A5: Date | B5: Project | C5: Cash flow (N$) | D5: Erf 1470 Khomasdal Net | E5: Excluding Erf 1470 Khomasdal
A6: =Ledger!A5 -> 43067 | B6: =Ledger!B5 -> Aromatic Fresh Notes Investments Pty Ltd - Erf 1470 Khomasdal | C6: =Ledger!C5 -> -45500000 | D6: =IF(B6="Erf 1470 Khomasdal",C6,0) -> 0 | E6: =-D6+C6 -> -45500000
A7: =Ledger!A6 -> 43067 | B7: =Ledger!B6 -> LIH- Nkurenkuru Ph 1 | C7: =Ledger!C6 -> -2200000 | D7: =IF(B7="Erf 1470 Khomasdal",C7,0) -> 0 | E7: =-D7+C7 -> -2200000
A8: =Ledger!A7 -> 43168 | B8: =Ledger!B7 -> Duma Tau — Kronlein | C8: =Ledger!C7 -> -22000000 | D8: =IF(B8="Erf 1470 Khomasdal",C8,0) -> 0 | E8: =-D8+C8 -> -22000000
A9: =Ledger!A8 -> 43216 | B9: =Ledger!B8 -> MPG _ Heaven's Ark — Otjomuise Lifestyle Estate | C9: =Ledger!C8 -> -10000000 | D9: =IF(B9="Erf 1470 Khomasdal",C9,0) -> 0 | E9: =-D9+C9 -> -10000000
A10: =Ledger!A9 -> 43280 | B10: =Ledger!B9 -> LIH- Nkurenkuru Ph 1 | C10: =Ledger!C9 -> -700000 | D10: =IF(B10="Erf 1470 Khomasdal",C10,0) -> 0 | E10: =-D10+C10 -> -700000
A11: =Ledger!A10 -> 43304 | B11: =Ledger!B10 -> LIH- Nkurenkuru Ph 1 | C11: =Ledger!C10 -> -4300000 | D11: =IF(B11="Erf 1470 Khomasdal",C11,0) -> 0 | E11: =-D11+C11 -> -4300000
A12: =Ledger!A11 -> 43322 | B12: =Ledger!B11 -> Duma Tau — Kronlein | C12: =Ledger!C11 -> -6000000 | D12: =IF(B12="Erf 1470 Khomasdal",C12,0) -> 0 | E12: =-D12+C12 -> -6000000
A13: =Ledger!A12 -> 43322 | B13: =Ledger!B12 -> LIH- Nkurenkuru Ph 1 | C13: =Ledger!C12 -> -5000000 | D13: =IF(B13="Erf 1470 Khomasdal",C13,0) -> 0 | E13: =-D13+C13 -> -5000000
A14: =Ledger!A13 -> 43356 | B14: =Ledger!B13 -> Duma Tau — Kronlein | C14: =Ledger!C13 -> 1302000 | D14: =IF(B14="Erf 1470 Khomasdal",C14,0) -> 0 | E14: =-D14+C14 -> 1302000
A15: =Ledger!A14 -> 43362 | B15: =Ledger!B14 -> Aromatic Fresh Notes Investments Pty Ltd - Erf 1470 Khomasdal | C15: =Ledger!C14 -> -1500000 | D15: =IF(B15="Erf 1470 Khomasdal",C15,0) -> 0 | E15: =-D15+C15 -> -1500000
A16: =Ledger!A15 -> 43362 | B16: =Ledger!B15 -> MPG _ Heaven's Ark — Otjomuise Lifestyle Estate | C16: =Ledger!C15 -> -1000000 | D16: =IF(B16="Erf 1470 Khomasdal",C16,0) -> 0 | E16: =-D16+C16 -> -1000000
A17: =Ledger!A16 -> 43384 | B17: =Ledger!B16 -> MPG _ Heaven's Ark — Otjomuise Lifestyle Estate | C17: =Ledger!C16 -> -10000000 | D17: =IF(B17="Erf 1470 Khomasdal",C17,0) -> 0 | E17: =-D17+C17 -> -10000000
... A109: =Ledger!A108 -> 46252 | B109: =Ledger!B108 -> Blue Mont Pty Ltd The Ridge | C109: =Ledger!C108 -> -7000000 | D109: =IF(B109="Erf 1470 Khomasdal",C109,0) -> 0 | E109: =-D109+C109 -> -7000000
A110: 46264 | B110: Revaluation : Profit Adjustment | C110: 0 | D110: =IF(B110="Erf 1470 Khomasdal",C110,0) -> 0 | E110: =+C110 -> 0
A111: =DATE(2026,7,30) -> 46233 | B111: RESIDUAL — portfolio carrying value (NAV), terminal cash flow | C111: 1.8410295e+08 | D111: =IF(B111="Erf 1470 Khomasdal",C111,0) -> 0 | E111: =-D111+C111 -> 1.8410295e+08
B112: TOTAL (incl. residual) | C112: =C111+SUM(C6:C109) -> 20898726
A114: B. CASH IRR & RESIDUAL — RESULTS
A115: Cash IRR, inception to 30-Sep-2026 (incl. residual) | C115: =XIRR(C6:C111,A6:A111) -> 0.032421145
A116: Residual / NAV excluding Khomasdal Erf 1470 | C116: =XIRR(E7:E111,A7:A111) -> 0.16933767
A118: TVPI | B118: =B119+B120 -> 1.0563302
A119: DPI | B119: =SUMIF(C6:C109,">0")/-SUMIF(C6:C109,"<0") -> 0.56010143
A120: RVPI | B120: =C111/-SUMIF(C6:C109,"<0") -> 0.49622872
A121: MOIC | B121: =(SUMIF(C6:C109,">0")+C111)/-SUMIF(C6:C109,"<0") -> 1.0563302

Sheet Statement_of_Cash_F_-_July_2026
A1: Statement of Cash Flows
A2: Konigstein Affordable Housing Fund
A3: For the 3 Months ended 31 July 2026
A5: Account | B5: 3 MONTHS ENDED | C5: YEAR ENDED
B6: 46234 | C6: 46022
A7: Operating Activities
A8: Payments to suppliers and employees | B8: -380249.58 | C8: -4695005
A9: Interest Received | C9: 1580113
A10: Net Cash Flows from Operating Activities | B10: =SUM(B8:B9) -> -380249.58 | C10: =SUM(C8:C9) -> -3114892
A12: Investing Activities
A13: Erf 1470 Khomasdal | B13: -500000 | C13: 8902639.4
A14: Nkurenkulu Ext 2-Phase 2-Lithon | B14: 0 | C14: -78279.71
A15: Dunescape Villas-Swakopmund | B15: -5900000 | C15: 20520366
A16: Turnstone | B16: 0 | C16: -13968610
A17: PAM Tree | B17: 3262978.1 | C17: -23328666
A18: Rocky Crest Windhoek-Blue Mont | B18: 0 | C18: 0
A19: Block 9-Swakopmund | B19: -4389111.1
A20: Otjomuise Ext 10-Margo Cove | B20: -4888879.3
A21: Net Cash Flows from Investing Activities | B21: =SUM(B13:B20) -> -12415012 | C21: =SUM(C13:C20) -> -7952550.5
A23: Financing Activities
A24: Other cash items from financing activities
A25: Capital Drawdowns/(Distributions) | B25: 23000000 | C25: 35632938
A26: Net Cash Flows from Financing Activities | B26: =SUM(B25) -> 23000000 | C26: =SUM(C25) -> 35632938
A28: Net Cash Flows | B28: =SUM(B10+B21+B26) -> 10204738 | C28: =SUM(C10+C21+C26) -> 24565496
A30: Cash and Cash Equivalents
A31: Cash and cash equivalents at beginning of period | B31: 56832421 | C31: 11258687
A32: Net change in cash for period | B32: =B28 -> 10204738 | C32: 24046054
A33: Cash and cash equivalents at end of period | B33: =B31+B32 -> 67037159 | C33: =SUM(C31:C32) -> 35304741

Sheet Profit_and_Loss_Jul_2026
A1: Detailed Income Statement
A2: Konigstein Affordable Housing Fund
A3: For the 3 Months ended 31 July 2026
A5: Account | B5: 3 MONTHS ENDED | C5: YEAR ENDED
B6: 46234 | C6: 46022
A7: Revenue
A8: Erf 1470 Khomasdal | B8: =468506.7+4713656.07-4713656.07 -> 468506.7 | C8: 16724749
A9: Nkurenkulu Ext 2-Phase 2-Lithon | B9: 62481.84 | C9: 365629.4
A10: Dunescape Villas-Swakopmund | B10: 0 | C10: 2427143.3
A11: Turnstone | B11: 0 | C11: 939942.93
A12: Block 9-CBreeze Swakopmund | B12: 1192.78
A13: Otjomuise Ext 10-Mago Cove | B13: 81603.09
A14: PAM TREE-Kuisebmund | B14: 745978.88
A15: Total Revenue | B15: =SUM(B8:B14) -> 1359763.3 | C15: =SUM(C8:C14) -> 20457465
A17: Operating Expenses
A18: Administrative Expenses
A19: Accounting Fees | B19: 4772.5 | C19: 60978
A20: Bank Charges | B20: 1805.02 | C20: 3617.7
A21: Management Fee | B21: 1247896.1 | C21: 6401193.8
A22: Total Administrative Expenses | B22: =SUM(B19:B21) -> 1254473.6 | C22: =SUM(C19:C21) -> 6465789.5
A24: Other Expenses
A25: Trustee Fees | B25: 34597 | C25: 88274.38
A26: Meeting Expenses | B26: 0 | C26: 3920
A27: Consulting Fees | B27: 0 | C27: 12075
A28: Legal Fees | B28: 0 | C28: 16560
A29: Audit Fees | B29: 460391.91 | C29: 282712.55
A30: NCCC Committee member Sitting fees | B30: 2152.5 | C30: 13125
A31: Transaction Expense | B31: 2444.05 | C31: 62359.18
A32: Total Other Expenses | B32: =SUM(B25:B31) -> 499585.46 | C32: =SUM(C25:C31) -> 479026.11
A34: Profit/(Loss)from Opperating Expenses | B34: =SUM(B15-B22-B32) -> -394295.74 | C34: =SUM(C15-C22-C32) -> 13512649
A36: Finance Income
A37: Interest Received from Cash and Cash Equivalent | B37: =90959.47+1037215.83 -> 1128175.3 | C37: 1580113
A39: Net Profit/ (Loss) | B39: =SUM(B34+B37) -> 733879.56 | C39: =SUM(C34+C37) -> 15092762

Sheet Balance_Sheet_July_2026
A1: Statement of Financial Position
A2: Konigstein Affordable Housing Fund
A3: As at 31 July 2026
B5: Account | C5: 46234 | D5: 46022
A7: Assets | E7: Net Profit
B8: Fixed Assets
B9: Erf 1470 Khomasdal | C9: =7637141.86+100-6457938.26+122372439.11-83446221.78 -> 40105521 | D9: 51356035
B10: Nkurenkuru Extension 2 -Phase 2 | C10: 1037365.9 | D10: 875383.15
B11: Dunescape Villas- Mondessa Swakopmund | C11: =12958783.82+100 -> 12958884 | D11: 5069869
B12: Turnstone Villas-Mossy wood | C12: =2618331.89+2293395.82+100 -> 4911827.7 | D12: 17247230
B13: PAM TREE | C13: 35672548 | D13: 23328666
B14: Rocky Chrest Windhoek-Blue Mont | C14: 13022186 | D14: 0
B15: Block 9 - Swakopmund | C15: 4290303.9 | D15: 0
B16: Otjomuise Ext 10 - Margo Cove | C16: 4827159.7 | D16: 0
A17: Total Fixed Assets | C17: =SUM(C9:C16) -> 1.168258e+08 | D17: =SUM(D9:D16) -> 97877183
B19: Current Assets
B20: Cash and Cash Equivalent | C20: =13517440.96+53519717.75 -> 67037159 | D20: 35754741
B21: Accounts Receivable | C21: 240000 | D21: 0
A22: Total Current Assets | C22: =SUM(C20:C21) -> 67277159 | D22: =SUM(D20:D21) -> 35754741
A23: Total Assets | C23: =C17+C22 -> 1.8410295e+08 | D23: =D17+D22 -> 1.3363192e+08
A25: Equity
B26: Capital Account: GIPF | C26: 1.8807294e+08 | D26: 1.3896403e+08
B27: Capital Account: Konigstein Capital | C27: 1880750 | D27: 1389661
B28: Current Year Earnings | C28: 1201303.2 | D28: 0
B29: Retained Income | C29: -7294346.5 | D29: -6721762
A30: Total Equity+ Liability | C30: =SUM(C26:C29)+C34 -> 1.8410295e+08 | D30: =SUM(D26:D29) -> 1.3363192e+08
A32: Liabilities
B33: Accounts Payable | C33: 242311.53 | D33: 0
A34: Total Current Liabilities | C34: =SUM(C33:C33) -> 242311.53 | D34: =SUM(D33:D33) -> 0
A36: Net Assets | C36: =C23-C34 -> 1.8386064e+08 | D36: =D23-D34 -> 1.3363192e+08
A38: Source: Konigstein Affordable Housing Fund - Balance Sheet as at 31 July 2026 (uploaded file), uploaded 7 September 2026
